{
 "1555": [
  [
   "keras/backend/common.py",
   48,
   "floatx",
   1555
  ],
  [
   [
    "keras/backend/common.py",
    61
   ]
  ]
 ],
 "1553": [
  [
   "keras/backend/common.py",
   13,
   "epsilon",
   1553
  ],
  [
   [
    "keras/backend/common.py",
    25
   ]
  ]
 ],
 "1558": [
  [
   "keras/backend/common.py",
   113,
   "image_data_format",
   1558
  ],
  [
   [
    "keras/backend/common.py",
    125
   ]
  ]
 ],
 "1556": [
  [
   "keras/backend/common.py",
   64,
   "set_floatx",
   1556
  ],
  [
   [
    "keras/backend/common.py",
    80
   ],
   [
    "keras/backend/common.py",
    81
   ],
   [
    "keras/backend/common.py",
    83
   ],
   [
    "keras/backend/common.py",
    82
   ]
  ]
 ],
 "1554": [
  [
   "keras/backend/common.py",
   28,
   "set_epsilon",
   1554
  ],
  [
   [
    "keras/backend/common.py",
    44
   ],
   [
    "keras/backend/common.py",
    45
   ]
  ]
 ],
 "1559": [
  [
   "keras/backend/common.py",
   128,
   "set_image_data_format",
   1559
  ],
  [
   [
    "keras/backend/common.py",
    144
   ],
   [
    "keras/backend/common.py",
    145
   ],
   [
    "keras/backend/common.py",
    147
   ]
  ]
 ],
 "430": [
  [
   "keras/legacy/interfaces.py",
   13,
   "generate_legacy_interface",
   430
  ],
  [
   [
    "keras/legacy/interfaces.py",
    18
   ],
   [
    "keras/legacy/interfaces.py",
    21
   ],
   [
    "keras/legacy/interfaces.py",
    22
   ],
   [
    "keras/legacy/interfaces.py",
    23
   ],
   [
    "keras/legacy/interfaces.py",
    24
   ],
   [
    "keras/legacy/interfaces.py",
    94
   ],
   [
    "keras/legacy/interfaces.py",
    19
   ]
  ]
 ],
 "431": [
  [
   "keras/legacy/interfaces.py",
   26,
   "legacy_support",
   431
  ],
  [
   [
    "keras/legacy/interfaces.py",
    92
   ],
   [
    "keras/legacy/interfaces.py",
    93
   ]
  ]
 ],
 "1384": [
  [
   "keras/backend/__init__.py",
   111,
   "backend",
   1384
  ],
  [
   [
    "keras/backend/__init__.py",
    124
   ]
  ]
 ],
 "223": [
  [
   "keras/applications/__init__.py",
   20,
   "keras_modules_injection",
   223
  ],
  [
   [
    "keras/applications/__init__.py",
    30
   ]
  ]
 ],
 "956": [
  [
   "keras/utils/test_utils.py",
   138,
   "keras_test",
   956
  ],
  [
   [
    "keras/utils/test_utils.py",
    153
   ]
  ]
 ],
 "1406": [
  [
   "keras/backend/tensorflow_backend.py",
   483,
   "placeholder",
   1406
  ],
  [
   [
    "keras/backend/tensorflow_backend.py",
    509
   ],
   [
    "keras/backend/tensorflow_backend.py",
    510
   ],
   [
    "keras/backend/tensorflow_backend.py",
    511
   ],
   [
    "keras/backend/tensorflow_backend.py",
    512
   ],
   [
    "keras/backend/tensorflow_backend.py",
    514
   ],
   [
    "keras/backend/tensorflow_backend.py",
    517
   ],
   [
    "keras/backend/tensorflow_backend.py",
    518
   ],
   [
    "keras/backend/tensorflow_backend.py",
    519
   ],
   [
    "keras/backend/tensorflow_backend.py",
    520
   ]
  ]
 ],
 "1500": [
  [
   "keras/backend/tensorflow_backend.py",
   2685,
   "function",
   1500
  ],
  [
   [
    "keras/backend/tensorflow_backend.py",
    2700
   ],
   [
    "keras/backend/tensorflow_backend.py",
    2701
   ],
   [
    "keras/backend/tensorflow_backend.py",
    2702
   ],
   [
    "keras/backend/tensorflow_backend.py",
    2705
   ]
  ]
 ],
 "1021": [
  [
   "keras/utils/generic_utils.py",
   244,
   "has_arg",
   1021
  ],
  [
   [
    "keras/utils/generic_utils.py",
    262
   ],
   [
    "keras/utils/generic_utils.py",
    267
   ],
   [
    "keras/utils/generic_utils.py",
    274
   ],
   [
    "keras/utils/generic_utils.py",
    275
   ],
   [
    "keras/utils/generic_utils.py",
    276
   ],
   [
    "keras/utils/generic_utils.py",
    282
   ]
  ]
 ],
 "1495": [
  [
   "keras/backend/tensorflow_backend.py",
   2510,
   "__init__",
   1495
  ],
  [
   [
    "keras/backend/tensorflow_backend.py",
    2514
   ],
   [
    "keras/backend/tensorflow_backend.py",
    2515
   ],
   [
    "keras/backend/tensorflow_backend.py",
    2518
   ],
   [
    "keras/backend/tensorflow_backend.py",
    2521
   ],
   [
    "keras/backend/tensorflow_backend.py",
    2524
   ],
   [
    "keras/backend/tensorflow_backend.py",
    2525
   ],
   [
    "keras/backend/tensorflow_backend.py",
    2526
   ],
   [
    "keras/backend/tensorflow_backend.py",
    2527
   ],
   [
    "keras/backend/tensorflow_backend.py",
    2528
   ],
   [
    "keras/backend/tensorflow_backend.py",
    2535
   ],
   [
    "keras/backend/tensorflow_backend.py",
    2536
   ],
   [
    "keras/backend/tensorflow_backend.py",
    2538
   ],
   [
    "keras/backend/tensorflow_backend.py",
    2540
   ],
   [
    "keras/backend/tensorflow_backend.py",
    2541
   ],
   [
    "keras/backend/tensorflow_backend.py",
    2547
   ],
   [
    "keras/backend/tensorflow_backend.py",
    2548
   ],
   [
    "keras/backend/tensorflow_backend.py",
    2549
   ],
   [
    "keras/backend/tensorflow_backend.py",
    2550
   ],
   [
    "keras/backend/tensorflow_backend.py",
    2553
   ],
   [
    "keras/backend/tensorflow_backend.py",
    2554
   ],
   [
    "keras/backend/tensorflow_backend.py",
    2555
   ],
   [
    "keras/backend/tensorflow_backend.py",
    2556
   ],
   [
    "keras/backend/tensorflow_backend.py",
    2557
   ],
   [
    "keras/backend/tensorflow_backend.py",
    2529
   ],
   [
    "keras/backend/tensorflow_backend.py",
    2530
   ],
   [
    "keras/backend/tensorflow_backend.py",
    2531
   ]
  ]
 ],
 "1402": [
  [
   "keras/backend/tensorflow_backend.py",
   363,
   "variable",
   1402
  ],
  [
   [
    "keras/backend/tensorflow_backend.py",
    390
   ],
   [
    "keras/backend/tensorflow_backend.py",
    391
   ],
   [
    "keras/backend/tensorflow_backend.py",
    392
   ],
   [
    "keras/backend/tensorflow_backend.py",
    402
   ],
   [
    "keras/backend/tensorflow_backend.py",
    403
   ],
   [
    "keras/backend/tensorflow_backend.py",
    404
   ],
   [
    "keras/backend/tensorflow_backend.py",
    407
   ],
   [
    "keras/backend/tensorflow_backend.py",
    409
   ],
   [
    "keras/backend/tensorflow_backend.py",
    410
   ],
   [
    "keras/backend/tensorflow_backend.py",
    412
   ],
   [
    "keras/backend/tensorflow_backend.py",
    413
   ],
   [
    "keras/backend/tensorflow_backend.py",
    405
   ],
   [
    "keras/backend/tensorflow_backend.py",
    406
   ]
  ]
 ],
 "1449": [
  [
   "keras/backend/tensorflow_backend.py",
   1506,
   "logsumexp",
   1449
  ],
  [
   [
    "keras/backend/tensorflow_backend.py",
    1524
   ]
  ]
 ],
 "1412": [
  [
   "keras/backend/tensorflow_backend.py",
   655,
   "eval",
   1412
  ],
  [
   [
    "keras/backend/tensorflow_backend.py",
    673
   ]
  ]
 ],
 "1401": [
  [
   "keras/backend/tensorflow_backend.py",
   334,
   "to_dense",
   1401
  ],
  [
   [
    "keras/backend/tensorflow_backend.py",
    354
   ],
   [
    "keras/backend/tensorflow_backend.py",
    357
   ]
  ]
 ],
 "1400": [
  [
   "keras/backend/tensorflow_backend.py",
   311,
   "is_sparse",
   1400
  ],
  [
   [
    "keras/backend/tensorflow_backend.py",
    331
   ]
  ]
 ],
 "1391": [
  [
   "keras/backend/tensorflow_backend.py",
   156,
   "get_session",
   1391
  ],
  [
   [
    "keras/backend/tensorflow_backend.py",
    172
   ],
   [
    "keras/backend/tensorflow_backend.py",
    174
   ],
   [
    "keras/backend/tensorflow_backend.py",
    176
   ],
   [
    "keras/backend/tensorflow_backend.py",
    179
   ],
   [
    "keras/backend/tensorflow_backend.py",
    180
   ],
   [
    "keras/backend/tensorflow_backend.py",
    181
   ],
   [
    "keras/backend/tensorflow_backend.py",
    186
   ],
   [
    "keras/backend/tensorflow_backend.py",
    187
   ],
   [
    "keras/backend/tensorflow_backend.py",
    188
   ],
   [
    "keras/backend/tensorflow_backend.py",
    189
   ],
   [
    "keras/backend/tensorflow_backend.py",
    190
   ],
   [
    "keras/backend/tensorflow_backend.py",
    191
   ],
   [
    "keras/backend/tensorflow_backend.py",
    192
   ],
   [
    "keras/backend/tensorflow_backend.py",
    193
   ],
   [
    "keras/backend/tensorflow_backend.py",
    194
   ],
   [
    "keras/backend/tensorflow_backend.py",
    195
   ],
   [
    "keras/backend/tensorflow_backend.py",
    198
   ],
   [
    "keras/backend/tensorflow_backend.py",
    200
   ],
   [
    "keras/backend/tensorflow_backend.py",
    201
   ],
   [
    "keras/backend/tensorflow_backend.py",
    202
   ],
   [
    "keras/backend/tensorflow_backend.py",
    203
   ],
   [
    "keras/backend/tensorflow_backend.py",
    204
   ],
   [
    "keras/backend/tensorflow_backend.py",
    205
   ],
   [
    "keras/backend/tensorflow_backend.py",
    206
   ],
   [
    "keras/backend/tensorflow_backend.py",
    209
   ],
   [
    "keras/backend/tensorflow_backend.py",
    211
   ]
  ]
 ],
 "1546": [
  [
   "keras/backend/tensorflow_backend.py",
   4165,
   "ctc_batch_cost",
   1546
  ],
  [
   [
    "keras/backend/tensorflow_backend.py",
    4182
   ],
   [
    "keras/backend/tensorflow_backend.py",
    4183
   ],
   [
    "keras/backend/tensorflow_backend.py",
    4184
   ],
   [
    "keras/backend/tensorflow_backend.py",
    4186
   ],
   [
    "keras/backend/tensorflow_backend.py",
    4188
   ]
  ]
 ],
 "1544": [
  [
   "keras/backend/tensorflow_backend.py",
   4128,
   "ctc_label_dense_to_sparse",
   1544
  ],
  [
   [
    "keras/backend/tensorflow_backend.py",
    4138
   ],
   [
    "keras/backend/tensorflow_backend.py",
    4139
   ],
   [
    "keras/backend/tensorflow_backend.py",
    4140
   ],
   [
    "keras/backend/tensorflow_backend.py",
    4146
   ],
   [
    "keras/backend/tensorflow_backend.py",
    4147
   ],
   [
    "keras/backend/tensorflow_backend.py",
    4149
   ],
   [
    "keras/backend/tensorflow_backend.py",
    4151
   ],
   [
    "keras/backend/tensorflow_backend.py",
    4153
   ],
   [
    "keras/backend/tensorflow_backend.py",
    4155
   ],
   [
    "keras/backend/tensorflow_backend.py",
    4157
   ],
   [
    "keras/backend/tensorflow_backend.py",
    4158
   ],
   [
    "keras/backend/tensorflow_backend.py",
    4160
   ],
   [
    "keras/backend/tensorflow_backend.py",
    4162
   ]
  ]
 ],
 "1545": [
  [
   "keras/backend/tensorflow_backend.py",
   4142,
   "range_less_than",
   1545
  ],
  [
   [
    "keras/backend/tensorflow_backend.py",
    4143
   ]
  ]
 ],
 "1487": [
  [
   "keras/backend/tensorflow_backend.py",
   2339,
   "reverse",
   1487
  ],
  [
   [
    "keras/backend/tensorflow_backend.py",
    2350
   ],
   [
    "keras/backend/tensorflow_backend.py",
    2351
   ],
   [
    "keras/backend/tensorflow_backend.py",
    2352
   ]
  ]
 ],
 "1469": [
  [
   "keras/backend/tensorflow_backend.py",
   1916,
   "concatenate",
   1469
  ],
  [
   [
    "keras/backend/tensorflow_backend.py",
    1926
   ],
   [
    "keras/backend/tensorflow_backend.py",
    1933
   ],
   [
    "keras/backend/tensorflow_backend.py",
    1936
   ],
   [
    "keras/backend/tensorflow_backend.py",
    1927
   ],
   [
    "keras/backend/tensorflow_backend.py",
    1928
   ],
   [
    "keras/backend/tensorflow_backend.py",
    1929
   ]
  ]
 ],
 "1532": [
  [
   "keras/backend/tensorflow_backend.py",
   3653,
   "separable_conv1d",
   1532
  ],
  [
   [
    "keras/backend/tensorflow_backend.py",
    3673
   ],
   [
    "keras/backend/tensorflow_backend.py",
    3674
   ],
   [
    "keras/backend/tensorflow_backend.py",
    3675
   ],
   [
    "keras/backend/tensorflow_backend.py",
    3676
   ],
   [
    "keras/backend/tensorflow_backend.py",
    3677
   ],
   [
    "keras/backend/tensorflow_backend.py",
    3679
   ],
   [
    "keras/backend/tensorflow_backend.py",
    3680
   ],
   [
    "keras/backend/tensorflow_backend.py",
    3681
   ],
   [
    "keras/backend/tensorflow_backend.py",
    3684
   ],
   [
    "keras/backend/tensorflow_backend.py",
    3685
   ],
   [
    "keras/backend/tensorflow_backend.py",
    3686
   ],
   [
    "keras/backend/tensorflow_backend.py",
    3687
   ],
   [
    "keras/backend/tensorflow_backend.py",
    3691
   ],
   [
    "keras/backend/tensorflow_backend.py",
    3692
   ],
   [
    "keras/backend/tensorflow_backend.py",
    3693
   ],
   [
    "keras/backend/tensorflow_backend.py",
    3694
   ],
   [
    "keras/backend/tensorflow_backend.py",
    3696
   ],
   [
    "keras/backend/tensorflow_backend.py",
    3702
   ],
   [
    "keras/backend/tensorflow_backend.py",
    3704
   ],
   [
    "keras/backend/tensorflow_backend.py",
    3707
   ]
  ]
 ],
 "1560": [
  [
   "keras/backend/common.py",
   150,
   "normalize_data_format",
   1560
  ],
  [
   [
    "keras/backend/common.py",
    171
   ],
   [
    "keras/backend/common.py",
    173
   ],
   [
    "keras/backend/common.py",
    174
   ],
   [
    "keras/backend/common.py",
    178
   ],
   [
    "keras/backend/common.py",
    175
   ],
   [
    "keras/backend/common.py",
    172
   ]
  ]
 ],
 "1525": [
  [
   "keras/backend/tensorflow_backend.py",
   3413,
   "_preprocess_conv1d_input",
   1525
  ],
  [
   [
    "keras/backend/tensorflow_backend.py",
    3424
   ],
   [
    "keras/backend/tensorflow_backend.py",
    3427
   ],
   [
    "keras/backend/tensorflow_backend.py",
    3428
   ],
   [
    "keras/backend/tensorflow_backend.py",
    3433
   ]
  ]
 ],
 "1411": [
  [
   "keras/backend/tensorflow_backend.py",
   625,
   "dtype",
   1411
  ],
  [
   [
    "keras/backend/tensorflow_backend.py",
    652
   ]
  ]
 ],
 "1528": [
  [
   "keras/backend/tensorflow_backend.py",
   3484,
   "_preprocess_padding",
   1528
  ],
  [
   [
    "keras/backend/tensorflow_backend.py",
    3496
   ],
   [
    "keras/backend/tensorflow_backend.py",
    3497
   ],
   [
    "keras/backend/tensorflow_backend.py",
    3502
   ],
   [
    "keras/backend/tensorflow_backend.py",
    3498
   ],
   [
    "keras/backend/tensorflow_backend.py",
    3499
   ],
   [
    "keras/backend/tensorflow_backend.py",
    3501
   ]
  ]
 ],
 "957": [
  [
   "keras/utils/test_utils.py",
   148,
   "wrapper",
   957
  ],
  [
   [
    "keras/utils/test_utils.py",
    149
   ],
   [
    "keras/utils/test_utils.py",
    150
   ],
   [
    "keras/utils/test_utils.py",
    151
   ],
   [
    "keras/utils/test_utils.py",
    152
   ]
  ]
 ],
 "1431": [
  [
   "keras/backend/tensorflow_backend.py",
   1234,
   "max",
   1431
  ],
  [
   [
    "keras/backend/tensorflow_backend.py",
    1248
   ]
  ]
 ],
 "1387": [
  [
   "keras/backend/tensorflow_backend.py",
   88,
   "clear_session",
   1387
  ],
  [
   [
    "keras/backend/tensorflow_backend.py",
    93
   ],
   [
    "keras/backend/tensorflow_backend.py",
    94
   ],
   [
    "keras/backend/tensorflow_backend.py",
    95
   ],
   [
    "keras/backend/tensorflow_backend.py",
    96
   ],
   [
    "keras/backend/tensorflow_backend.py",
    97
   ],
   [
    "keras/backend/tensorflow_backend.py",
    98
   ],
   [
    "keras/backend/tensorflow_backend.py",
    101
   ],
   [
    "keras/backend/tensorflow_backend.py",
    102
   ]
  ]
 ],
 "1386": [
  [
   "keras/backend/tensorflow_backend.py",
   81,
   "reset_uids",
   1386
  ],
  [
   [
    "keras/backend/tensorflow_backend.py",
    84
   ],
   [
    "keras/backend/tensorflow_backend.py",
    85
   ]
  ]
 ],
 "1432": [
  [
   "keras/backend/tensorflow_backend.py",
   1251,
   "min",
   1432
  ],
  [
   [
    "keras/backend/tensorflow_backend.py",
    1265
   ]
  ]
 ],
 "1439": [
  [
   "keras/backend/tensorflow_backend.py",
   1368,
   "mean",
   1439
  ],
  [
   [
    "keras/backend/tensorflow_backend.py",
    1382
   ],
   [
    "keras/backend/tensorflow_backend.py",
    1384
   ]
  ]
 ],
 "1438": [
  [
   "keras/backend/tensorflow_backend.py",
   1351,
   "std",
   1438
  ],
  [
   [
    "keras/backend/tensorflow_backend.py",
    1365
   ]
  ]
 ],
 "1437": [
  [
   "keras/backend/tensorflow_backend.py",
   1328,
   "var",
   1437
  ],
  [
   [
    "keras/backend/tensorflow_backend.py",
    1342
   ],
   [
    "keras/backend/tensorflow_backend.py",
    1344
   ],
   [
    "keras/backend/tensorflow_backend.py",
    1345
   ],
   [
    "keras/backend/tensorflow_backend.py",
    1346
   ]
  ]
 ],
 "1434": [
  [
   "keras/backend/tensorflow_backend.py",
   1285,
   "prod",
   1434
  ],
  [
   [
    "keras/backend/tensorflow_backend.py",
    1299
   ]
  ]
 ],
 "1440": [
  [
   "keras/backend/tensorflow_backend.py",
   1387,
   "any",
   1440
  ],
  [
   [
    "keras/backend/tensorflow_backend.py",
    1398
   ],
   [
    "keras/backend/tensorflow_backend.py",
    1399
   ]
  ]
 ],
 "1441": [
  [
   "keras/backend/tensorflow_backend.py",
   1402,
   "all",
   1441
  ],
  [
   [
    "keras/backend/tensorflow_backend.py",
    1413
   ],
   [
    "keras/backend/tensorflow_backend.py",
    1414
   ]
  ]
 ],
 "1442": [
  [
   "keras/backend/tensorflow_backend.py",
   1417,
   "argmax",
   1442
  ],
  [
   [
    "keras/backend/tensorflow_backend.py",
    1427
   ]
  ]
 ],
 "1443": [
  [
   "keras/backend/tensorflow_backend.py",
   1430,
   "argmin",
   1443
  ],
  [
   [
    "keras/backend/tensorflow_backend.py",
    1440
   ]
  ]
 ],
 "1444": [
  [
   "keras/backend/tensorflow_backend.py",
   1443,
   "square",
   1444
  ],
  [
   [
    "keras/backend/tensorflow_backend.py",
    1452
   ]
  ]
 ],
 "1445": [
  [
   "keras/backend/tensorflow_backend.py",
   1455,
   "abs",
   1445
  ],
  [
   [
    "keras/backend/tensorflow_backend.py",
    1464
   ]
  ]
 ],
 "1446": [
  [
   "keras/backend/tensorflow_backend.py",
   1467,
   "sqrt",
   1446
  ],
  [
   [
    "keras/backend/tensorflow_backend.py",
    1476
   ],
   [
    "keras/backend/tensorflow_backend.py",
    1477
   ],
   [
    "keras/backend/tensorflow_backend.py",
    1478
   ],
   [
    "keras/backend/tensorflow_backend.py",
    1479
   ]
  ]
 ],
 "1399": [
  [
   "keras/backend/tensorflow_backend.py",
   298,
   "_to_tensor",
   1399
  ],
  [
   [
    "keras/backend/tensorflow_backend.py",
    308
   ]
  ]
 ],
 "1447": [
  [
   "keras/backend/tensorflow_backend.py",
   1482,
   "exp",
   1447
  ],
  [
   [
    "keras/backend/tensorflow_backend.py",
    1491
   ]
  ]
 ],
 "1450": [
  [
   "keras/backend/tensorflow_backend.py",
   1527,
   "round",
   1450
  ],
  [
   [
    "keras/backend/tensorflow_backend.py",
    1538
   ]
  ]
 ],
 "1451": [
  [
   "keras/backend/tensorflow_backend.py",
   1541,
   "sign",
   1451
  ],
  [
   [
    "keras/backend/tensorflow_backend.py",
    1550
   ]
  ]
 ],
 "1452": [
  [
   "keras/backend/tensorflow_backend.py",
   1553,
   "pow",
   1452
  ],
  [
   [
    "keras/backend/tensorflow_backend.py",
    1563
   ]
  ]
 ],
 "1453": [
  [
   "keras/backend/tensorflow_backend.py",
   1566,
   "clip",
   1453
  ],
  [
   [
    "keras/backend/tensorflow_backend.py",
    1577
   ],
   [
    "keras/backend/tensorflow_backend.py",
    1579
   ],
   [
    "keras/backend/tensorflow_backend.py",
    1581
   ],
   [
    "keras/backend/tensorflow_backend.py",
    1582
   ],
   [
    "keras/backend/tensorflow_backend.py",
    1583
   ]
  ]
 ],
 "1454": [
  [
   "keras/backend/tensorflow_backend.py",
   1586,
   "equal",
   1454
  ],
  [
   [
    "keras/backend/tensorflow_backend.py",
    1596
   ]
  ]
 ],
 "1455": [
  [
   "keras/backend/tensorflow_backend.py",
   1599,
   "not_equal",
   1455
  ],
  [
   [
    "keras/backend/tensorflow_backend.py",
    1609
   ]
  ]
 ],
 "1456": [
  [
   "keras/backend/tensorflow_backend.py",
   1612,
   "greater",
   1456
  ],
  [
   [
    "keras/backend/tensorflow_backend.py",
    1622
   ]
  ]
 ],
 "1457": [
  [
   "keras/backend/tensorflow_backend.py",
   1625,
   "greater_equal",
   1457
  ],
  [
   [
    "keras/backend/tensorflow_backend.py",
    1635
   ]
  ]
 ],
 "1458": [
  [
   "keras/backend/tensorflow_backend.py",
   1638,
   "less",
   1458
  ],
  [
   [
    "keras/backend/tensorflow_backend.py",
    1648
   ]
  ]
 ],
 "1459": [
  [
   "keras/backend/tensorflow_backend.py",
   1651,
   "less_equal",
   1459
  ],
  [
   [
    "keras/backend/tensorflow_backend.py",
    1661
   ]
  ]
 ],
 "1460": [
  [
   "keras/backend/tensorflow_backend.py",
   1664,
   "maximum",
   1460
  ],
  [
   [
    "keras/backend/tensorflow_backend.py",
    1674
   ]
  ]
 ],
 "1461": [
  [
   "keras/backend/tensorflow_backend.py",
   1677,
   "minimum",
   1461
  ],
  [
   [
    "keras/backend/tensorflow_backend.py",
    1687
   ]
  ]
 ],
 "1510": [
  [
   "keras/backend/tensorflow_backend.py",
   3090,
   "in_test_phase",
   1510
  ],
  [
   [
    "keras/backend/tensorflow_backend.py",
    3107
   ]
  ]
 ],
 "1509": [
  [
   "keras/backend/tensorflow_backend.py",
   3047,
   "in_train_phase",
   1509
  ],
  [
   [
    "keras/backend/tensorflow_backend.py",
    3065
   ],
   [
    "keras/backend/tensorflow_backend.py",
    3069
   ],
   [
    "keras/backend/tensorflow_backend.py",
    3071
   ],
   [
    "keras/backend/tensorflow_backend.py",
    3072
   ],
   [
    "keras/backend/tensorflow_backend.py",
    3075
   ],
   [
    "keras/backend/tensorflow_backend.py",
    3077
   ],
   [
    "keras/backend/tensorflow_backend.py",
    3078
   ],
   [
    "keras/backend/tensorflow_backend.py",
    3081
   ]
  ]
 ],
 "1537": [
  [
   "keras/backend/tensorflow_backend.py",
   3877,
   "pool2d",
   1537
  ],
  [
   [
    "keras/backend/tensorflow_backend.py",
    3897
   ],
   [
    "keras/backend/tensorflow_backend.py",
    3899
   ],
   [
    "keras/backend/tensorflow_backend.py",
    3900
   ],
   [
    "keras/backend/tensorflow_backend.py",
    3901
   ],
   [
    "keras/backend/tensorflow_backend.py",
    3902
   ],
   [
    "keras/backend/tensorflow_backend.py",
    3903
   ],
   [
    "keras/backend/tensorflow_backend.py",
    3908
   ],
   [
    "keras/backend/tensorflow_backend.py",
    3909
   ],
   [
    "keras/backend/tensorflow_backend.py",
    3919
   ],
   [
    "keras/backend/tensorflow_backend.py",
    3921
   ],
   [
    "keras/backend/tensorflow_backend.py",
    3912
   ],
   [
    "keras/backend/tensorflow_backend.py",
    3913
   ],
   [
    "keras/backend/tensorflow_backend.py",
    3917
   ],
   [
    "keras/backend/tensorflow_backend.py",
    3920
   ]
  ]
 ],
 "1526": [
  [
   "keras/backend/tensorflow_backend.py",
   3436,
   "_preprocess_conv2d_input",
   1526
  ],
  [
   [
    "keras/backend/tensorflow_backend.py",
    3449
   ],
   [
    "keras/backend/tensorflow_backend.py",
    3452
   ],
   [
    "keras/backend/tensorflow_backend.py",
    3453
   ],
   [
    "keras/backend/tensorflow_backend.py",
    3458
   ],
   [
    "keras/backend/tensorflow_backend.py",
    3454
   ],
   [
    "keras/backend/tensorflow_backend.py",
    3455
   ]
  ]
 ],
 "1529": [
  [
   "keras/backend/tensorflow_backend.py",
   3505,
   "conv1d",
   1529
  ],
  [
   [
    "keras/backend/tensorflow_backend.py",
    3524
   ],
   [
    "keras/backend/tensorflow_backend.py",
    3526
   ],
   [
    "keras/backend/tensorflow_backend.py",
    3527
   ],
   [
    "keras/backend/tensorflow_backend.py",
    3536
   ],
   [
    "keras/backend/tensorflow_backend.py",
    3537
   ],
   [
    "keras/backend/tensorflow_backend.py",
    3538
   ],
   [
    "keras/backend/tensorflow_backend.py",
    3546
   ],
   [
    "keras/backend/tensorflow_backend.py",
    3548
   ]
  ]
 ],
 "1415": [
  [
   "keras/backend/tensorflow_backend.py",
   740,
   "eye",
   1415
  ],
  [
   [
    "keras/backend/tensorflow_backend.py",
    762
   ],
   [
    "keras/backend/tensorflow_backend.py",
    763
   ],
   [
    "keras/backend/tensorflow_backend.py",
    764
   ],
   [
    "keras/backend/tensorflow_backend.py",
    765
   ]
  ]
 ],
 "1409": [
  [
   "keras/backend/tensorflow_backend.py",
   569,
   "int_shape",
   1409
  ],
  [
   [
    "keras/backend/tensorflow_backend.py",
    590
   ],
   [
    "keras/backend/tensorflow_backend.py",
    592
   ],
   [
    "keras/backend/tensorflow_backend.py",
    593
   ],
   [
    "keras/backend/tensorflow_backend.py",
    591
   ]
  ]
 ],
 "1419": [
  [
   "keras/backend/tensorflow_backend.py",
   831,
   "random_uniform_variable",
   1419
  ],
  [
   [
    "keras/backend/tensorflow_backend.py",
    857
   ],
   [
    "keras/backend/tensorflow_backend.py",
    858
   ],
   [
    "keras/backend/tensorflow_backend.py",
    859
   ],
   [
    "keras/backend/tensorflow_backend.py",
    860
   ],
   [
    "keras/backend/tensorflow_backend.py",
    862
   ],
   [
    "keras/backend/tensorflow_backend.py",
    863
   ],
   [
    "keras/backend/tensorflow_backend.py",
    865
   ]
  ]
 ],
 "1420": [
  [
   "keras/backend/tensorflow_backend.py",
   868,
   "random_normal_variable",
   1420
  ],
  [
   [
    "keras/backend/tensorflow_backend.py",
    894
   ],
   [
    "keras/backend/tensorflow_backend.py",
    895
   ],
   [
    "keras/backend/tensorflow_backend.py",
    896
   ],
   [
    "keras/backend/tensorflow_backend.py",
    897
   ],
   [
    "keras/backend/tensorflow_backend.py",
    899
   ],
   [
    "keras/backend/tensorflow_backend.py",
    900
   ],
   [
    "keras/backend/tensorflow_backend.py",
    902
   ]
  ]
 ],
 "1418": [
  [
   "keras/backend/tensorflow_backend.py",
   818,
   "identity",
   1418
  ],
  [
   [
    "keras/backend/tensorflow_backend.py",
    828
   ]
  ]
 ],
 "1499": [
  [
   "keras/backend/tensorflow_backend.py",
   2667,
   "__call__",
   1499
  ],
  [
   [
    "keras/backend/tensorflow_backend.py",
    2668
   ],
   [
    "keras/backend/tensorflow_backend.py",
    2669
   ],
   [
    "keras/backend/tensorflow_backend.py",
    2676
   ]
  ]
 ],
 "1497": [
  [
   "keras/backend/tensorflow_backend.py",
   2606,
   "_call",
   1497
  ],
  [
   [
    "keras/backend/tensorflow_backend.py",
    2607
   ],
   [
    "keras/backend/tensorflow_backend.py",
    2610
   ],
   [
    "keras/backend/tensorflow_backend.py",
    2611
   ],
   [
    "keras/backend/tensorflow_backend.py",
    2612
   ],
   [
    "keras/backend/tensorflow_backend.py",
    2613
   ],
   [
    "keras/backend/tensorflow_backend.py",
    2614
   ],
   [
    "keras/backend/tensorflow_backend.py",
    2615
   ],
   [
    "keras/backend/tensorflow_backend.py",
    2616
   ],
   [
    "keras/backend/tensorflow_backend.py",
    2618
   ],
   [
    "keras/backend/tensorflow_backend.py",
    2623
   ],
   [
    "keras/backend/tensorflow_backend.py",
    2627
   ],
   [
    "keras/backend/tensorflow_backend.py",
    2630
   ],
   [
    "keras/backend/tensorflow_backend.py",
    2637
   ],
   [
    "keras/backend/tensorflow_backend.py",
    2642
   ],
   [
    "keras/backend/tensorflow_backend.py",
    2646
   ],
   [
    "keras/backend/tensorflow_backend.py",
    2647
   ],
   [
    "keras/backend/tensorflow_backend.py",
    2631
   ],
   [
    "keras/backend/tensorflow_backend.py",
    2632
   ]
  ]
 ],
 "1405": [
  [
   "keras/backend/tensorflow_backend.py",
   479,
   "is_tensor",
   1405
  ],
  [
   [
    "keras/backend/tensorflow_backend.py",
    480
   ]
  ]
 ],
 "1496": [
  [
   "keras/backend/tensorflow_backend.py",
   2559,
   "_make_callable",
   1496
  ],
  [
   [
    "keras/backend/tensorflow_backend.py",
    2574
   ],
   [
    "keras/backend/tensorflow_backend.py",
    2576
   ],
   [
    "keras/backend/tensorflow_backend.py",
    2577
   ],
   [
    "keras/backend/tensorflow_backend.py",
    2578
   ],
   [
    "keras/backend/tensorflow_backend.py",
    2582
   ],
   [
    "keras/backend/tensorflow_backend.py",
    2592
   ],
   [
    "keras/backend/tensorflow_backend.py",
    2593
   ],
   [
    "keras/backend/tensorflow_backend.py",
    2595
   ],
   [
    "keras/backend/tensorflow_backend.py",
    2597
   ],
   [
    "keras/backend/tensorflow_backend.py",
    2600
   ],
   [
    "keras/backend/tensorflow_backend.py",
    2601
   ],
   [
    "keras/backend/tensorflow_backend.py",
    2602
   ],
   [
    "keras/backend/tensorflow_backend.py",
    2603
   ],
   [
    "keras/backend/tensorflow_backend.py",
    2604
   ],
   [
    "keras/backend/tensorflow_backend.py",
    2579
   ],
   [
    "keras/backend/tensorflow_backend.py",
    2580
   ]
  ]
 ],
 "1549": [
  [
   "keras/backend/tensorflow_backend.py",
   4257,
   "foldl",
   1549
  ],
  [
   [
    "keras/backend/tensorflow_backend.py",
    4270
   ]
  ]
 ],
 "1535": [
  [
   "keras/backend/tensorflow_backend.py",
   3789,
   "conv3d",
   1535
  ],
  [
   [
    "keras/backend/tensorflow_backend.py",
    3810
   ],
   [
    "keras/backend/tensorflow_backend.py",
    3812
   ],
   [
    "keras/backend/tensorflow_backend.py",
    3813
   ],
   [
    "keras/backend/tensorflow_backend.py",
    3814
   ],
   [
    "keras/backend/tensorflow_backend.py",
    3821
   ],
   [
    "keras/backend/tensorflow_backend.py",
    3823
   ],
   [
    "keras/backend/tensorflow_backend.py",
    3822
   ]
  ]
 ],
 "1527": [
  [
   "keras/backend/tensorflow_backend.py",
   3461,
   "_preprocess_conv3d_input",
   1527
  ],
  [
   [
    "keras/backend/tensorflow_backend.py",
    3472
   ],
   [
    "keras/backend/tensorflow_backend.py",
    3475
   ],
   [
    "keras/backend/tensorflow_backend.py",
    3476
   ],
   [
    "keras/backend/tensorflow_backend.py",
    3481
   ],
   [
    "keras/backend/tensorflow_backend.py",
    3477
   ],
   [
    "keras/backend/tensorflow_backend.py",
    3478
   ]
  ]
 ],
 "1530": [
  [
   "keras/backend/tensorflow_backend.py",
   3551,
   "conv2d",
   1530
  ],
  [
   [
    "keras/backend/tensorflow_backend.py",
    3572
   ],
   [
    "keras/backend/tensorflow_backend.py",
    3574
   ],
   [
    "keras/backend/tensorflow_backend.py",
    3576
   ],
   [
    "keras/backend/tensorflow_backend.py",
    3577
   ],
   [
    "keras/backend/tensorflow_backend.py",
    3585
   ],
   [
    "keras/backend/tensorflow_backend.py",
    3587
   ],
   [
    "keras/backend/tensorflow_backend.py",
    3586
   ]
  ]
 ],
 "1540": [
  [
   "keras/backend/tensorflow_backend.py",
   4030,
   "random_normal",
   1540
  ],
  [
   [
    "keras/backend/tensorflow_backend.py",
    4044
   ],
   [
    "keras/backend/tensorflow_backend.py",
    4045
   ],
   [
    "keras/backend/tensorflow_backend.py",
    4046
   ],
   [
    "keras/backend/tensorflow_backend.py",
    4048
   ]
  ]
 ],
 "1435": [
  [
   "keras/backend/tensorflow_backend.py",
   1302,
   "cumsum",
   1435
  ],
  [
   [
    "keras/backend/tensorflow_backend.py",
    1312
   ]
  ]
 ],
 "1436": [
  [
   "keras/backend/tensorflow_backend.py",
   1315,
   "cumprod",
   1436
  ],
  [
   [
    "keras/backend/tensorflow_backend.py",
    1325
   ]
  ]
 ],
 "1482": [
  [
   "keras/backend/tensorflow_backend.py",
   2227,
   "temporal_padding",
   1482
  ],
  [
   [
    "keras/backend/tensorflow_backend.py",
    2238
   ],
   [
    "keras/backend/tensorflow_backend.py",
    2239
   ],
   [
    "keras/backend/tensorflow_backend.py",
    2240
   ]
  ]
 ],
 "1543": [
  [
   "keras/backend/tensorflow_backend.py",
   4096,
   "truncated_normal",
   1543
  ],
  [
   [
    "keras/backend/tensorflow_backend.py",
    4114
   ],
   [
    "keras/backend/tensorflow_backend.py",
    4115
   ],
   [
    "keras/backend/tensorflow_backend.py",
    4116
   ],
   [
    "keras/backend/tensorflow_backend.py",
    4118
   ]
  ]
 ],
 "1547": [
  [
   "keras/backend/tensorflow_backend.py",
   4193,
   "ctc_decode",
   1547
  ],
  [
   [
    "keras/backend/tensorflow_backend.py",
    4222
   ],
   [
    "keras/backend/tensorflow_backend.py",
    4223
   ],
   [
    "keras/backend/tensorflow_backend.py",
    4225
   ],
   [
    "keras/backend/tensorflow_backend.py",
    4226
   ],
   [
    "keras/backend/tensorflow_backend.py",
    4235
   ],
   [
    "keras/backend/tensorflow_backend.py",
    4237
   ]
  ]
 ],
 "1542": [
  [
   "keras/backend/tensorflow_backend.py",
   4075,
   "random_binomial",
   1542
  ],
  [
   [
    "keras/backend/tensorflow_backend.py",
    4087
   ],
   [
    "keras/backend/tensorflow_backend.py",
    4088
   ],
   [
    "keras/backend/tensorflow_backend.py",
    4089
   ],
   [
    "keras/backend/tensorflow_backend.py",
    4090
   ],
   [
    "keras/backend/tensorflow_backend.py",
    4091
   ]
  ]
 ],
 "1533": [
  [
   "keras/backend/tensorflow_backend.py",
   3710,
   "separable_conv2d",
   1533
  ],
  [
   [
    "keras/backend/tensorflow_backend.py",
    3731
   ],
   [
    "keras/backend/tensorflow_backend.py",
    3733
   ],
   [
    "keras/backend/tensorflow_backend.py",
    3734
   ],
   [
    "keras/backend/tensorflow_backend.py",
    3735
   ],
   [
    "keras/backend/tensorflow_backend.py",
    3736
   ],
   [
    "keras/backend/tensorflow_backend.py",
    3740
   ],
   [
    "keras/backend/tensorflow_backend.py",
    3745
   ],
   [
    "keras/backend/tensorflow_backend.py",
    3747
   ],
   [
    "keras/backend/tensorflow_backend.py",
    3746
   ]
  ]
 ],
 "1398": [
  [
   "keras/backend/tensorflow_backend.py",
   282,
   "_has_nchw_support",
   1398
  ],
  [
   [
    "keras/backend/tensorflow_backend.py",
    291
   ],
   [
    "keras/backend/tensorflow_backend.py",
    292
   ],
   [
    "keras/backend/tensorflow_backend.py",
    293
   ]
  ]
 ],
 "1396": [
  [
   "keras/backend/tensorflow_backend.py",
   251,
   "_is_current_explicit_device",
   1396
  ],
  [
   [
    "keras/backend/tensorflow_backend.py",
    263
   ],
   [
    "keras/backend/tensorflow_backend.py",
    264
   ],
   [
    "keras/backend/tensorflow_backend.py",
    266
   ],
   [
    "keras/backend/tensorflow_backend.py",
    267
   ]
  ]
 ],
 "1395": [
  [
   "keras/backend/tensorflow_backend.py",
   237,
   "_get_current_tf_device",
   1395
  ],
  [
   [
    "keras/backend/tensorflow_backend.py",
    245
   ],
   [
    "keras/backend/tensorflow_backend.py",
    246
   ],
   [
    "keras/backend/tensorflow_backend.py",
    247
   ],
   [
    "keras/backend/tensorflow_backend.py",
    248
   ]
  ]
 ],
 "1393": [
  [
   "keras/backend/tensorflow_backend.py",
   229,
   "__init__",
   1393
  ],
  [
   [
    "keras/backend/tensorflow_backend.py",
    230
   ]
  ]
 ],
 "1397": [
  [
   "keras/backend/tensorflow_backend.py",
   270,
   "_get_available_gpus",
   1397
  ],
  [
   [
    "keras/backend/tensorflow_backend.py",
    276
   ],
   [
    "keras/backend/tensorflow_backend.py",
    277
   ],
   [
    "keras/backend/tensorflow_backend.py",
    278
   ],
   [
    "keras/backend/tensorflow_backend.py",
    279
   ]
  ]
 ],
 "1448": [
  [
   "keras/backend/tensorflow_backend.py",
   1494,
   "log",
   1448
  ],
  [
   [
    "keras/backend/tensorflow_backend.py",
    1503
   ]
  ]
 ],
 "1503": [
  [
   "keras/backend/tensorflow_backend.py",
   2740,
   "rnn",
   1503
  ],
  [
   [
    "keras/backend/tensorflow_backend.py",
    2787
   ],
   [
    "keras/backend/tensorflow_backend.py",
    2788
   ],
   [
    "keras/backend/tensorflow_backend.py",
    2793
   ],
   [
    "keras/backend/tensorflow_backend.py",
    2794
   ],
   [
    "keras/backend/tensorflow_backend.py",
    2796
   ],
   [
    "keras/backend/tensorflow_backend.py",
    2803
   ],
   [
    "keras/backend/tensorflow_backend.py",
    2804
   ],
   [
    "keras/backend/tensorflow_backend.py",
    2806
   ],
   [
    "keras/backend/tensorflow_backend.py",
    2807
   ],
   [
    "keras/backend/tensorflow_backend.py",
    2809
   ],
   [
    "keras/backend/tensorflow_backend.py",
    2877
   ],
   [
    "keras/backend/tensorflow_backend.py",
    2880
   ],
   [
    "keras/backend/tensorflow_backend.py",
    2882
   ],
   [
    "keras/backend/tensorflow_backend.py",
    2883
   ],
   [
    "keras/backend/tensorflow_backend.py",
    2884
   ],
   [
    "keras/backend/tensorflow_backend.py",
    2888
   ],
   [
    "keras/backend/tensorflow_backend.py",
    2892
   ],
   [
    "keras/backend/tensorflow_backend.py",
    2893
   ],
   [
    "keras/backend/tensorflow_backend.py",
    2895
   ],
   [
    "keras/backend/tensorflow_backend.py",
    2966
   ],
   [
    "keras/backend/tensorflow_backend.py",
    2973
   ],
   [
    "keras/backend/tensorflow_backend.py",
    2974
   ],
   [
    "keras/backend/tensorflow_backend.py",
    2975
   ],
   [
    "keras/backend/tensorflow_backend.py",
    2977
   ],
   [
    "keras/backend/tensorflow_backend.py",
    2978
   ],
   [
    "keras/backend/tensorflow_backend.py",
    2980
   ],
   [
    "keras/backend/tensorflow_backend.py",
    2981
   ],
   [
    "keras/backend/tensorflow_backend.py",
    2982
   ],
   [
    "keras/backend/tensorflow_backend.py",
    2983
   ],
   [
    "keras/backend/tensorflow_backend.py",
    2810
   ],
   [
    "keras/backend/tensorflow_backend.py",
    2813
   ],
   [
    "keras/backend/tensorflow_backend.py",
    2814
   ],
   [
    "keras/backend/tensorflow_backend.py",
    2815
   ],
   [
    "keras/backend/tensorflow_backend.py",
    2817
   ],
   [
    "keras/backend/tensorflow_backend.py",
    2818
   ],
   [
    "keras/backend/tensorflow_backend.py",
    2821
   ],
   [
    "keras/backend/tensorflow_backend.py",
    2866
   ],
   [
    "keras/backend/tensorflow_backend.py",
    2867
   ],
   [
    "keras/backend/tensorflow_backend.py",
    2868
   ],
   [
    "keras/backend/tensorflow_backend.py",
    2870
   ],
   [
    "keras/backend/tensorflow_backend.py",
    2871
   ],
   [
    "keras/backend/tensorflow_backend.py",
    2872
   ],
   [
    "keras/backend/tensorflow_backend.py",
    2873
   ],
   [
    "keras/backend/tensorflow_backend.py",
    2874
   ],
   [
    "keras/backend/tensorflow_backend.py",
    2878
   ],
   [
    "keras/backend/tensorflow_backend.py",
    2819
   ],
   [
    "keras/backend/tensorflow_backend.py",
    2797
   ],
   [
    "keras/backend/tensorflow_backend.py",
    2798
   ],
   [
    "keras/backend/tensorflow_backend.py",
    2799
   ],
   [
    "keras/backend/tensorflow_backend.py",
    2800
   ],
   [
    "keras/backend/tensorflow_backend.py",
    2801
   ],
   [
    "keras/backend/tensorflow_backend.py",
    2896
   ],
   [
    "keras/backend/tensorflow_backend.py",
    2903
   ],
   [
    "keras/backend/tensorflow_backend.py",
    2906
   ],
   [
    "keras/backend/tensorflow_backend.py",
    2910
   ],
   [
    "keras/backend/tensorflow_backend.py",
    2822
   ],
   [
    "keras/backend/tensorflow_backend.py",
    2823
   ],
   [
    "keras/backend/tensorflow_backend.py",
    2826
   ],
   [
    "keras/backend/tensorflow_backend.py",
    2827
   ],
   [
    "keras/backend/tensorflow_backend.py",
    2828
   ],
   [
    "keras/backend/tensorflow_backend.py",
    2841
   ],
   [
    "keras/backend/tensorflow_backend.py",
    2844
   ],
   [
    "keras/backend/tensorflow_backend.py",
    2845
   ],
   [
    "keras/backend/tensorflow_backend.py",
    2849
   ],
   [
    "keras/backend/tensorflow_backend.py",
    2851
   ],
   [
    "keras/backend/tensorflow_backend.py",
    2852
   ],
   [
    "keras/backend/tensorflow_backend.py",
    2854
   ],
   [
    "keras/backend/tensorflow_backend.py",
    2856
   ],
   [
    "keras/backend/tensorflow_backend.py",
    2859
   ],
   [
    "keras/backend/tensorflow_backend.py",
    2860
   ],
   [
    "keras/backend/tensorflow_backend.py",
    2861
   ],
   [
    "keras/backend/tensorflow_backend.py",
    2847
   ],
   [
    "keras/backend/tensorflow_backend.py",
    2862
   ],
   [
    "keras/backend/tensorflow_backend.py",
    2863
   ],
   [
    "keras/backend/tensorflow_backend.py",
    2864
   ]
  ]
 ],
 "1427": [
  [
   "keras/backend/tensorflow_backend.py",
   1019,
   "dot",
   1427
  ],
  [
   [
    "keras/backend/tensorflow_backend.py",
    1061
   ],
   [
    "keras/backend/tensorflow_backend.py",
    1082
   ],
   [
    "keras/backend/tensorflow_backend.py",
    1085
   ],
   [
    "keras/backend/tensorflow_backend.py",
    1086
   ],
   [
    "keras/backend/tensorflow_backend.py",
    1062
   ],
   [
    "keras/backend/tensorflow_backend.py",
    1063
   ],
   [
    "keras/backend/tensorflow_backend.py",
    1064
   ],
   [
    "keras/backend/tensorflow_backend.py",
    1065
   ],
   [
    "keras/backend/tensorflow_backend.py",
    1068
   ],
   [
    "keras/backend/tensorflow_backend.py",
    1069
   ],
   [
    "keras/backend/tensorflow_backend.py",
    1070
   ],
   [
    "keras/backend/tensorflow_backend.py",
    1071
   ],
   [
    "keras/backend/tensorflow_backend.py",
    1072
   ],
   [
    "keras/backend/tensorflow_backend.py",
    1075
   ],
   [
    "keras/backend/tensorflow_backend.py",
    1076
   ],
   [
    "keras/backend/tensorflow_backend.py",
    1077
   ],
   [
    "keras/backend/tensorflow_backend.py",
    1078
   ],
   [
    "keras/backend/tensorflow_backend.py",
    1079
   ],
   [
    "keras/backend/tensorflow_backend.py",
    1080
   ]
  ]
 ],
 "1410": [
  [
   "keras/backend/tensorflow_backend.py",
   598,
   "ndim",
   1410
  ],
  [
   [
    "keras/backend/tensorflow_backend.py",
    619
   ],
   [
    "keras/backend/tensorflow_backend.py",
    620
   ],
   [
    "keras/backend/tensorflow_backend.py",
    621
   ]
  ]
 ],
 "1505": [
  [
   "keras/backend/tensorflow_backend.py",
   2943,
   "_step",
   1505
  ],
  [
   [
    "keras/backend/tensorflow_backend.py",
    2954
   ],
   [
    "keras/backend/tensorflow_backend.py",
    2955
   ],
   [
    "keras/backend/tensorflow_backend.py",
    2958
   ],
   [
    "keras/backend/tensorflow_backend.py",
    2961
   ],
   [
    "keras/backend/tensorflow_backend.py",
    2962
   ],
   [
    "keras/backend/tensorflow_backend.py",
    2963
   ],
   [
    "keras/backend/tensorflow_backend.py",
    2964
   ]
  ]
 ],
 "1480": [
  [
   "keras/backend/tensorflow_backend.py",
   2201,
   "expand_dims",
   1480
  ],
  [
   [
    "keras/backend/tensorflow_backend.py",
    2211
   ]
  ]
 ],
 "1504": [
  [
   "keras/backend/tensorflow_backend.py",
   2912,
   "_step",
   1504
  ],
  [
   [
    "keras/backend/tensorflow_backend.py",
    2923
   ],
   [
    "keras/backend/tensorflow_backend.py",
    2924
   ],
   [
    "keras/backend/tensorflow_backend.py",
    2925
   ],
   [
    "keras/backend/tensorflow_backend.py",
    2928
   ],
   [
    "keras/backend/tensorflow_backend.py",
    2931
   ],
   [
    "keras/backend/tensorflow_backend.py",
    2932
   ],
   [
    "keras/backend/tensorflow_backend.py",
    2933
   ],
   [
    "keras/backend/tensorflow_backend.py",
    2935
   ],
   [
    "keras/backend/tensorflow_backend.py",
    2936
   ],
   [
    "keras/backend/tensorflow_backend.py",
    2940
   ],
   [
    "keras/backend/tensorflow_backend.py",
    2941
   ]
  ]
 ],
 "1416": [
  [
   "keras/backend/tensorflow_backend.py",
   768,
   "zeros_like",
   1416
  ],
  [
   [
    "keras/backend/tensorflow_backend.py",
    790
   ]
  ]
 ],
 "1538": [
  [
   "keras/backend/tensorflow_backend.py",
   3924,
   "pool3d",
   1538
  ],
  [
   [
    "keras/backend/tensorflow_backend.py",
    3943
   ],
   [
    "keras/backend/tensorflow_backend.py",
    3945
   ],
   [
    "keras/backend/tensorflow_backend.py",
    3946
   ],
   [
    "keras/backend/tensorflow_backend.py",
    3947
   ],
   [
    "keras/backend/tensorflow_backend.py",
    3948
   ],
   [
    "keras/backend/tensorflow_backend.py",
    3949
   ],
   [
    "keras/backend/tensorflow_backend.py",
    3954
   ],
   [
    "keras/backend/tensorflow_backend.py",
    3958
   ],
   [
    "keras/backend/tensorflow_backend.py",
    3959
   ],
   [
    "keras/backend/tensorflow_backend.py",
    3965
   ],
   [
    "keras/backend/tensorflow_backend.py",
    3966
   ],
   [
    "keras/backend/tensorflow_backend.py",
    3967
   ],
   [
    "keras/backend/tensorflow_backend.py",
    3955
   ],
   [
    "keras/backend/tensorflow_backend.py",
    3963
   ]
  ]
 ],
 "1423": [
  [
   "keras/backend/tensorflow_backend.py",
   963,
   "update",
   1423
  ],
  [
   [
    "keras/backend/tensorflow_backend.py",
    973
   ]
  ]
 ],
 "1534": [
  [
   "keras/backend/tensorflow_backend.py",
   3750,
   "depthwise_conv2d",
   1534
  ],
  [
   [
    "keras/backend/tensorflow_backend.py",
    3770
   ],
   [
    "keras/backend/tensorflow_backend.py",
    3772
   ],
   [
    "keras/backend/tensorflow_backend.py",
    3773
   ],
   [
    "keras/backend/tensorflow_backend.py",
    3774
   ],
   [
    "keras/backend/tensorflow_backend.py",
    3775
   ],
   [
    "keras/backend/tensorflow_backend.py",
    3779
   ],
   [
    "keras/backend/tensorflow_backend.py",
    3784
   ],
   [
    "keras/backend/tensorflow_backend.py",
    3786
   ],
   [
    "keras/backend/tensorflow_backend.py",
    3785
   ]
  ]
 ],
 "1550": [
  [
   "keras/backend/tensorflow_backend.py",
   4273,
   "foldr",
   1550
  ],
  [
   [
    "keras/backend/tensorflow_backend.py",
    4286
   ]
  ]
 ],
 "1472": [
  [
   "keras/backend/tensorflow_backend.py",
   1966,
   "resize_images",
   1472
  ],
  [
   [
    "keras/backend/tensorflow_backend.py",
    1986
   ],
   [
    "keras/backend/tensorflow_backend.py",
    1987
   ],
   [
    "keras/backend/tensorflow_backend.py",
    1991
   ],
   [
    "keras/backend/tensorflow_backend.py",
    1992
   ],
   [
    "keras/backend/tensorflow_backend.py",
    1993
   ],
   [
    "keras/backend/tensorflow_backend.py",
    1995
   ],
   [
    "keras/backend/tensorflow_backend.py",
    1996
   ],
   [
    "keras/backend/tensorflow_backend.py",
    1997
   ],
   [
    "keras/backend/tensorflow_backend.py",
    1998
   ],
   [
    "keras/backend/tensorflow_backend.py",
    2004
   ],
   [
    "keras/backend/tensorflow_backend.py",
    2005
   ],
   [
    "keras/backend/tensorflow_backend.py",
    2007
   ],
   [
    "keras/backend/tensorflow_backend.py",
    2010
   ],
   [
    "keras/backend/tensorflow_backend.py",
    2012
   ],
   [
    "keras/backend/tensorflow_backend.py",
    2015
   ],
   [
    "keras/backend/tensorflow_backend.py",
    2017
   ],
   [
    "keras/backend/tensorflow_backend.py",
    2018
   ],
   [
    "keras/backend/tensorflow_backend.py",
    2019
   ],
   [
    "keras/backend/tensorflow_backend.py",
    1989
   ]
  ]
 ],
 "1471": [
  [
   "keras/backend/tensorflow_backend.py",
   1952,
   "permute_dimensions",
   1471
  ],
  [
   [
    "keras/backend/tensorflow_backend.py",
    1963
   ]
  ]
 ],
 "1030": [
  [
   "keras/utils/generic_utils.py",
   537,
   "transpose_shape",
   1030
  ],
  [
   [
    "keras/utils/generic_utils.py",
    570
   ],
   [
    "keras/utils/generic_utils.py",
    571
   ],
   [
    "keras/utils/generic_utils.py",
    572
   ],
   [
    "keras/utils/generic_utils.py",
    573
   ],
   [
    "keras/utils/generic_utils.py",
    575
   ],
   [
    "keras/utils/generic_utils.py",
    577
   ],
   [
    "keras/utils/generic_utils.py",
    578
   ],
   [
    "keras/utils/generic_utils.py",
    579
   ],
   [
    "keras/utils/generic_utils.py",
    581
   ]
  ]
 ],
 "1486": [
  [
   "keras/backend/tensorflow_backend.py",
   2324,
   "one_hot",
   1486
  ],
  [
   [
    "keras/backend/tensorflow_backend.py",
    2336
   ]
  ]
 ],
 "1477": [
  [
   "keras/backend/tensorflow_backend.py",
   2158,
   "tile",
   1477
  ],
  [
   [
    "keras/backend/tensorflow_backend.py",
    2169
   ],
   [
    "keras/backend/tensorflow_backend.py",
    2171
   ]
  ]
 ],
 "1511": [
  [
   "keras/backend/tensorflow_backend.py",
   3112,
   "relu",
   1511
  ],
  [
   [
    "keras/backend/tensorflow_backend.py",
    3125
   ],
   [
    "keras/backend/tensorflow_backend.py",
    3126
   ],
   [
    "keras/backend/tensorflow_backend.py",
    3130
   ],
   [
    "keras/backend/tensorflow_backend.py",
    3131
   ],
   [
    "keras/backend/tensorflow_backend.py",
    3132
   ],
   [
    "keras/backend/tensorflow_backend.py",
    3133
   ]
  ]
 ],
 "1514": [
  [
   "keras/backend/tensorflow_backend.py",
   3167,
   "softplus",
   1514
  ],
  [
   [
    "keras/backend/tensorflow_backend.py",
    3176
   ]
  ]
 ],
 "1512": [
  [
   "keras/backend/tensorflow_backend.py",
   3136,
   "elu",
   1512
  ],
  [
   [
    "keras/backend/tensorflow_backend.py",
    3146
   ],
   [
    "keras/backend/tensorflow_backend.py",
    3147
   ],
   [
    "keras/backend/tensorflow_backend.py",
    3150
   ]
  ]
 ],
 "1519": [
  [
   "keras/backend/tensorflow_backend.py",
   3315,
   "sigmoid",
   1519
  ],
  [
   [
    "keras/backend/tensorflow_backend.py",
    3324
   ]
  ]
 ],
 "1520": [
  [
   "keras/backend/tensorflow_backend.py",
   3327,
   "hard_sigmoid",
   1520
  ],
  [
   [
    "keras/backend/tensorflow_backend.py",
    3340
   ],
   [
    "keras/backend/tensorflow_backend.py",
    3341
   ],
   [
    "keras/backend/tensorflow_backend.py",
    3342
   ],
   [
    "keras/backend/tensorflow_backend.py",
    3343
   ],
   [
    "keras/backend/tensorflow_backend.py",
    3344
   ]
  ]
 ],
 "1521": [
  [
   "keras/backend/tensorflow_backend.py",
   3347,
   "tanh",
   1521
  ],
  [
   [
    "keras/backend/tensorflow_backend.py",
    3356
   ]
  ]
 ],
 "1513": [
  [
   "keras/backend/tensorflow_backend.py",
   3153,
   "softmax",
   1513
  ],
  [
   [
    "keras/backend/tensorflow_backend.py",
    3164
   ]
  ]
 ],
 "1518": [
  [
   "keras/backend/tensorflow_backend.py",
   3290,
   "binary_crossentropy",
   1518
  ],
  [
   [
    "keras/backend/tensorflow_backend.py",
    3305
   ],
   [
    "keras/backend/tensorflow_backend.py",
    3311
   ],
   [
    "keras/backend/tensorflow_backend.py",
    3307
   ],
   [
    "keras/backend/tensorflow_backend.py",
    3308
   ],
   [
    "keras/backend/tensorflow_backend.py",
    3309
   ]
  ]
 ],
 "1516": [
  [
   "keras/backend/tensorflow_backend.py",
   3191,
   "categorical_crossentropy",
   1516
  ],
  [
   [
    "keras/backend/tensorflow_backend.py",
    3213
   ],
   [
    "keras/backend/tensorflow_backend.py",
    3214
   ],
   [
    "keras/backend/tensorflow_backend.py",
    3222
   ],
   [
    "keras/backend/tensorflow_backend.py",
    3230
   ],
   [
    "keras/backend/tensorflow_backend.py",
    3224
   ],
   [
    "keras/backend/tensorflow_backend.py",
    3226
   ],
   [
    "keras/backend/tensorflow_backend.py",
    3227
   ],
   [
    "keras/backend/tensorflow_backend.py",
    3228
   ]
  ]
 ],
 "1523": [
  [
   "keras/backend/tensorflow_backend.py",
   3381,
   "l2_normalize",
   1523
  ],
  [
   [
    "keras/backend/tensorflow_backend.py",
    3391
   ]
  ]
 ],
 "1414": [
  [
   "keras/backend/tensorflow_backend.py",
   708,
   "ones",
   1414
  ],
  [
   [
    "keras/backend/tensorflow_backend.py",
    731
   ],
   [
    "keras/backend/tensorflow_backend.py",
    732
   ],
   [
    "keras/backend/tensorflow_backend.py",
    733
   ],
   [
    "keras/backend/tensorflow_backend.py",
    734
   ],
   [
    "keras/backend/tensorflow_backend.py",
    735
   ],
   [
    "keras/backend/tensorflow_backend.py",
    736
   ]
  ]
 ],
 "1428": [
  [
   "keras/backend/tensorflow_backend.py",
   1089,
   "batch_dot",
   1428
  ],
  [
   [
    "keras/backend/tensorflow_backend.py",
    1140
   ],
   [
    "keras/backend/tensorflow_backend.py",
    1141
   ],
   [
    "keras/backend/tensorflow_backend.py",
    1142
   ],
   [
    "keras/backend/tensorflow_backend.py",
    1143
   ],
   [
    "keras/backend/tensorflow_backend.py",
    1144
   ],
   [
    "keras/backend/tensorflow_backend.py",
    1147
   ],
   [
    "keras/backend/tensorflow_backend.py",
    1151
   ],
   [
    "keras/backend/tensorflow_backend.py",
    1154
   ],
   [
    "keras/backend/tensorflow_backend.py",
    1158
   ],
   [
    "keras/backend/tensorflow_backend.py",
    1159
   ],
   [
    "keras/backend/tensorflow_backend.py",
    1160
   ],
   [
    "keras/backend/tensorflow_backend.py",
    1161
   ],
   [
    "keras/backend/tensorflow_backend.py",
    1172
   ],
   [
    "keras/backend/tensorflow_backend.py",
    1178
   ],
   [
    "keras/backend/tensorflow_backend.py",
    1179
   ],
   [
    "keras/backend/tensorflow_backend.py",
    1180
   ],
   [
    "keras/backend/tensorflow_backend.py",
    1163
   ],
   [
    "keras/backend/tensorflow_backend.py",
    1165
   ],
   [
    "keras/backend/tensorflow_backend.py",
    1166
   ],
   [
    "keras/backend/tensorflow_backend.py",
    1167
   ],
   [
    "keras/backend/tensorflow_backend.py",
    1171
   ],
   [
    "keras/backend/tensorflow_backend.py",
    1152
   ],
   [
    "keras/backend/tensorflow_backend.py",
    1153
   ],
   [
    "keras/backend/tensorflow_backend.py",
    1173
   ],
   [
    "keras/backend/tensorflow_backend.py",
    1174
   ],
   [
    "keras/backend/tensorflow_backend.py",
    1177
   ],
   [
    "keras/backend/tensorflow_backend.py",
    1155
   ],
   [
    "keras/backend/tensorflow_backend.py",
    1156
   ],
   [
    "keras/backend/tensorflow_backend.py",
    1176
   ]
  ]
 ],
 "1506": [
  [
   "keras/backend/tensorflow_backend.py",
   2986,
   "switch",
   1506
  ],
  [
   [
    "keras/backend/tensorflow_backend.py",
    3003
   ],
   [
    "keras/backend/tensorflow_backend.py",
    3005
   ],
   [
    "keras/backend/tensorflow_backend.py",
    3006
   ],
   [
    "keras/backend/tensorflow_backend.py",
    3007
   ],
   [
    "keras/backend/tensorflow_backend.py",
    3012
   ],
   [
    "keras/backend/tensorflow_backend.py",
    3017
   ],
   [
    "keras/backend/tensorflow_backend.py",
    3044
   ],
   [
    "keras/backend/tensorflow_backend.py",
    3024
   ],
   [
    "keras/backend/tensorflow_backend.py",
    3026
   ],
   [
    "keras/backend/tensorflow_backend.py",
    3028
   ],
   [
    "keras/backend/tensorflow_backend.py",
    3029
   ],
   [
    "keras/backend/tensorflow_backend.py",
    3035
   ],
   [
    "keras/backend/tensorflow_backend.py",
    3036
   ],
   [
    "keras/backend/tensorflow_backend.py",
    3037
   ],
   [
    "keras/backend/tensorflow_backend.py",
    3038
   ],
   [
    "keras/backend/tensorflow_backend.py",
    3039
   ],
   [
    "keras/backend/tensorflow_backend.py",
    3040
   ],
   [
    "keras/backend/tensorflow_backend.py",
    3041
   ],
   [
    "keras/backend/tensorflow_backend.py",
    3042
   ],
   [
    "keras/backend/tensorflow_backend.py",
    3043
   ]
  ]
 ],
 "1507": [
  [
   "keras/backend/tensorflow_backend.py",
   3008,
   "then_expression_fn",
   1507
  ],
  [
   [
    "keras/backend/tensorflow_backend.py",
    3009
   ]
  ]
 ],
 "1508": [
  [
   "keras/backend/tensorflow_backend.py",
   3013,
   "else_expression_fn",
   1508
  ],
  [
   [
    "keras/backend/tensorflow_backend.py",
    3014
   ]
  ]
 ],
 "1522": [
  [
   "keras/backend/tensorflow_backend.py",
   3359,
   "dropout",
   1522
  ],
  [
   [
    "keras/backend/tensorflow_backend.py",
    3373
   ],
   [
    "keras/backend/tensorflow_backend.py",
    3374
   ],
   [
    "keras/backend/tensorflow_backend.py",
    3375
   ],
   [
    "keras/backend/tensorflow_backend.py",
    3378
   ]
  ]
 ],
 "1390": [
  [
   "keras/backend/tensorflow_backend.py",
   140,
   "set_learning_phase",
   1390
  ],
  [
   [
    "keras/backend/tensorflow_backend.py",
    149
   ],
   [
    "keras/backend/tensorflow_backend.py",
    150
   ],
   [
    "keras/backend/tensorflow_backend.py",
    151
   ]
  ]
 ],
 "1404": [
  [
   "keras/backend/tensorflow_backend.py",
   433,
   "is_keras_tensor",
   1404
  ],
  [
   [
    "keras/backend/tensorflow_backend.py",
    472
   ],
   [
    "keras/backend/tensorflow_backend.py",
    473
   ],
   [
    "keras/backend/tensorflow_backend.py",
    476
   ]
  ]
 ],
 "1502": [
  [
   "keras/backend/tensorflow_backend.py",
   2721,
   "stop_gradient",
   1502
  ],
  [
   [
    "keras/backend/tensorflow_backend.py",
    2732
   ],
   [
    "keras/backend/tensorflow_backend.py",
    2733
   ],
   [
    "keras/backend/tensorflow_backend.py",
    2735
   ]
  ]
 ],
 "1429": [
  [
   "keras/backend/tensorflow_backend.py",
   1183,
   "transpose",
   1429
  ],
  [
   [
    "keras/backend/tensorflow_backend.py",
    1215
   ]
  ]
 ],
 "1430": [
  [
   "keras/backend/tensorflow_backend.py",
   1218,
   "gather",
   1430
  ],
  [
   [
    "keras/backend/tensorflow_backend.py",
    1228
   ]
  ]
 ],
 "1474": [
  [
   "keras/backend/tensorflow_backend.py",
   2052,
   "repeat_elements",
   1474
  ],
  [
   [
    "keras/backend/tensorflow_backend.py",
    2066
   ],
   [
    "keras/backend/tensorflow_backend.py",
    2068
   ],
   [
    "keras/backend/tensorflow_backend.py",
    2070
   ],
   [
    "keras/backend/tensorflow_backend.py",
    2072
   ],
   [
    "keras/backend/tensorflow_backend.py",
    2073
   ],
   [
    "keras/backend/tensorflow_backend.py",
    2081
   ],
   [
    "keras/backend/tensorflow_backend.py",
    2082
   ],
   [
    "keras/backend/tensorflow_backend.py",
    2083
   ],
   [
    "keras/backend/tensorflow_backend.py",
    2084
   ],
   [
    "keras/backend/tensorflow_backend.py",
    2085
   ],
   [
    "keras/backend/tensorflow_backend.py",
    2086
   ],
   [
    "keras/backend/tensorflow_backend.py",
    2089
   ],
   [
    "keras/backend/tensorflow_backend.py",
    2090
   ],
   [
    "keras/backend/tensorflow_backend.py",
    2091
   ],
   [
    "keras/backend/tensorflow_backend.py",
    2092
   ],
   [
    "keras/backend/tensorflow_backend.py",
    2093
   ],
   [
    "keras/backend/tensorflow_backend.py",
    2096
   ],
   [
    "keras/backend/tensorflow_backend.py",
    2097
   ],
   [
    "keras/backend/tensorflow_backend.py",
    2098
   ],
   [
    "keras/backend/tensorflow_backend.py",
    2099
   ]
  ]
 ],
 "1489": [
  [
   "keras/backend/tensorflow_backend.py",
   2378,
   "get_value",
   1489
  ],
  [
   [
    "keras/backend/tensorflow_backend.py",
    2387
   ]
  ]
 ],
 "1421": [
  [
   "keras/backend/tensorflow_backend.py",
   905,
   "count_params",
   1421
  ],
  [
   [
    "keras/backend/tensorflow_backend.py",
    925
   ]
  ]
 ],
 "1493": [
  [
   "keras/backend/tensorflow_backend.py",
   2453,
   "get_variable_shape",
   1493
  ],
  [
   [
    "keras/backend/tensorflow_backend.py",
    2462
   ]
  ]
 ],
 "1494": [
  [
   "keras/backend/tensorflow_backend.py",
   2465,
   "print_tensor",
   1494
  ],
  [
   [
    "keras/backend/tensorflow_backend.py",
    2484
   ]
  ]
 ],
 "1548": [
  [
   "keras/backend/tensorflow_backend.py",
   4242,
   "map_fn",
   1548
  ],
  [
   [
    "keras/backend/tensorflow_backend.py",
    4254
   ]
  ]
 ],
 "1433": [
  [
   "keras/backend/tensorflow_backend.py",
   1268,
   "sum",
   1433
  ],
  [
   [
    "keras/backend/tensorflow_backend.py",
    1282
   ]
  ]
 ],
 "1476": [
  [
   "keras/backend/tensorflow_backend.py",
   2121,
   "arange",
   1476
  ],
  [
   [
    "keras/backend/tensorflow_backend.py",
    2142
   ],
   [
    "keras/backend/tensorflow_backend.py",
    2143
   ],
   [
    "keras/backend/tensorflow_backend.py",
    2144
   ],
   [
    "keras/backend/tensorflow_backend.py",
    2152
   ],
   [
    "keras/backend/tensorflow_backend.py",
    2153
   ],
   [
    "keras/backend/tensorflow_backend.py",
    2155
   ],
   [
    "keras/backend/tensorflow_backend.py",
    2145
   ],
   [
    "keras/backend/tensorflow_backend.py",
    2154
   ],
   [
    "keras/backend/tensorflow_backend.py",
    2148
   ]
  ]
 ],
 "1539": [
  [
   "keras/backend/tensorflow_backend.py",
   3970,
   "bias_add",
   1539
  ],
  [
   [
    "keras/backend/tensorflow_backend.py",
    3988
   ],
   [
    "keras/backend/tensorflow_backend.py",
    3989
   ],
   [
    "keras/backend/tensorflow_backend.py",
    3990
   ],
   [
    "keras/backend/tensorflow_backend.py",
    3993
   ],
   [
    "keras/backend/tensorflow_backend.py",
    4000
   ],
   [
    "keras/backend/tensorflow_backend.py",
    4016
   ],
   [
    "keras/backend/tensorflow_backend.py",
    4024
   ],
   [
    "keras/backend/tensorflow_backend.py",
    4025
   ],
   [
    "keras/backend/tensorflow_backend.py",
    4017
   ],
   [
    "keras/backend/tensorflow_backend.py",
    4018
   ],
   [
    "keras/backend/tensorflow_backend.py",
    4021
   ],
   [
    "keras/backend/tensorflow_backend.py",
    4022
   ],
   [
    "keras/backend/tensorflow_backend.py",
    4001
   ],
   [
    "keras/backend/tensorflow_backend.py",
    4002
   ],
   [
    "keras/backend/tensorflow_backend.py",
    4003
   ],
   [
    "keras/backend/tensorflow_backend.py",
    4007
   ],
   [
    "keras/backend/tensorflow_backend.py",
    3994
   ],
   [
    "keras/backend/tensorflow_backend.py",
    3995
   ],
   [
    "keras/backend/tensorflow_backend.py",
    3998
   ],
   [
    "keras/backend/tensorflow_backend.py",
    3999
   ],
   [
    "keras/backend/tensorflow_backend.py",
    4020
   ],
   [
    "keras/backend/tensorflow_backend.py",
    4010
   ],
   [
    "keras/backend/tensorflow_backend.py",
    4011
   ],
   [
    "keras/backend/tensorflow_backend.py",
    4012
   ]
  ]
 ],
 "1470": [
  [
   "keras/backend/tensorflow_backend.py",
   1939,
   "reshape",
   1470
  ],
  [
   [
    "keras/backend/tensorflow_backend.py",
    1949
   ]
  ]
 ],
 "1422": [
  [
   "keras/backend/tensorflow_backend.py",
   928,
   "cast",
   1422
  ],
  [
   [
    "keras/backend/tensorflow_backend.py",
    957
   ]
  ]
 ],
 "1403": [
  [
   "keras/backend/tensorflow_backend.py",
   416,
   "constant",
   1403
  ],
  [
   [
    "keras/backend/tensorflow_backend.py",
    428
   ],
   [
    "keras/backend/tensorflow_backend.py",
    430
   ]
  ]
 ],
 "1475": [
  [
   "keras/backend/tensorflow_backend.py",
   2102,
   "repeat",
   1475
  ],
  [
   [
    "keras/backend/tensorflow_backend.py",
    2115
   ],
   [
    "keras/backend/tensorflow_backend.py",
    2116
   ],
   [
    "keras/backend/tensorflow_backend.py",
    2117
   ],
   [
    "keras/backend/tensorflow_backend.py",
    2118
   ]
  ]
 ],
 "1478": [
  [
   "keras/backend/tensorflow_backend.py",
   2174,
   "flatten",
   1478
  ],
  [
   [
    "keras/backend/tensorflow_backend.py",
    2183
   ]
  ]
 ],
 "1479": [
  [
   "keras/backend/tensorflow_backend.py",
   2186,
   "batch_flatten",
   1479
  ],
  [
   [
    "keras/backend/tensorflow_backend.py",
    2197
   ],
   [
    "keras/backend/tensorflow_backend.py",
    2198
   ]
  ]
 ],
 "1408": [
  [
   "keras/backend/tensorflow_backend.py",
   538,
   "shape",
   1408
  ],
  [
   [
    "keras/backend/tensorflow_backend.py",
    566
   ]
  ]
 ],
 "1481": [
  [
   "keras/backend/tensorflow_backend.py",
   2214,
   "squeeze",
   1481
  ],
  [
   [
    "keras/backend/tensorflow_backend.py",
    2224
   ]
  ]
 ],
 "1473": [
  [
   "keras/backend/tensorflow_backend.py",
   2022,
   "resize_volumes",
   1473
  ],
  [
   [
    "keras/backend/tensorflow_backend.py",
    2038
   ],
   [
    "keras/backend/tensorflow_backend.py",
    2039
   ],
   [
    "keras/backend/tensorflow_backend.py",
    2040
   ],
   [
    "keras/backend/tensorflow_backend.py",
    2041
   ],
   [
    "keras/backend/tensorflow_backend.py",
    2042
   ],
   [
    "keras/backend/tensorflow_backend.py",
    2043
   ],
   [
    "keras/backend/tensorflow_backend.py",
    2044
   ],
   [
    "keras/backend/tensorflow_backend.py",
    2045
   ],
   [
    "keras/backend/tensorflow_backend.py",
    2046
   ],
   [
    "keras/backend/tensorflow_backend.py",
    2047
   ],
   [
    "keras/backend/tensorflow_backend.py",
    2049
   ]
  ]
 ],
 "1541": [
  [
   "keras/backend/tensorflow_backend.py",
   4052,
   "random_uniform",
   1541
  ],
  [
   [
    "keras/backend/tensorflow_backend.py",
    4067
   ],
   [
    "keras/backend/tensorflow_backend.py",
    4068
   ],
   [
    "keras/backend/tensorflow_backend.py",
    4069
   ],
   [
    "keras/backend/tensorflow_backend.py",
    4070
   ],
   [
    "keras/backend/tensorflow_backend.py",
    4071
   ]
  ]
 ]
}