{
 "matplotlib_21": {
  "line": {
   "Tarantula": {
    "best_case": {
     "top-1": 0.0,
     "top-5": 0.0,
     "top-10": 0.0,
     "top-200": 0.9343,
     "exam": 0.002530674846625767,
     "wasted-effort": 270
    },
    "avg_case": {
     "top-1": 0.0,
     "top-5": 0.0,
     "top-10": 0.0,
     "top-200": 0.4930000000000018,
     "exam": 0.5587346625766871,
     "wasted-effort": 65200
    },
    "worst_case": {
     "top-1": 0.0,
     "top-5": 0.0,
     "top-10": 0.0,
     "top-200": 0.24919999999999967,
     "exam": 0.5587346625766871,
     "wasted-effort": 65200
    }
   },
   "Ochiai": {
    "best_case": {
     "top-1": 0.0,
     "top-5": 0.0,
     "top-10": 0.0,
     "top-200": 0.9319,
     "exam": 0.002530674846625767,
     "wasted-effort": 270
    },
    "avg_case": {
     "top-1": 0.0,
     "top-5": 0.0,
     "top-10": 0.0,
     "top-200": 0.4985333333333351,
     "exam": 0.5587346625766871,
     "wasted-effort": 65200
    },
    "worst_case": {
     "top-1": 0.0,
     "top-5": 0.0,
     "top-10": 0.0,
     "top-200": 0.2469333333333343,
     "exam": 0.5587346625766871,
     "wasted-effort": 65200
    }
   },
   "DStar": {
    "best_case": {
     "top-1": 0.0,
     "top-5": 0.0,
     "top-10": 0.0,
     "top-200": 0.9403,
     "exam": 0.0025,
     "wasted-effort": 268
    },
    "avg_case": {
     "top-1": 0.0,
     "top-5": 0.0,
     "top-10": 0.0,
     "top-200": 0.4991000000000011,
     "exam": 0.5587346625766871,
     "wasted-effort": 65200
    },
    "worst_case": {
     "top-1": 0.0,
     "top-5": 0.0,
     "top-10": 0.0,
     "top-200": 0.24791666666666798,
     "exam": 0.5587346625766871,
     "wasted-effort": 65200
    }
   },
   "Naish1": {
    "best_case": {
     "top-1": 0.0,
     "top-5": 0.0,
     "top-10": 0.0,
     "top-200": 0.934,
     "exam": 0.002530674846625767,
     "wasted-effort": 270
    },
    "avg_case": {
     "top-1": 0.0,
     "top-5": 0.0,
     "top-10": 0.0,
     "top-200": 0.4927333333333334,
     "exam": 0.5587346625766871,
     "wasted-effort": 65200
    },
    "worst_case": {
     "top-1": 0.0,
     "top-5": 0.0,
     "top-10": 0.0,
     "top-200": 0.2488500000000001,
     "exam": 0.5587346625766871,
     "wasted-effort": 65200
    }
   },
   "Naish2": {
    "best_case": {
     "top-1": 0.0,
     "top-5": 0.0,
     "top-10": 0.0,
     "top-200": 0.9391,
     "exam": 0.002530674846625767,
     "wasted-effort": 270
    },
    "avg_case": {
     "top-1": 0.0,
     "top-5": 0.0,
     "top-10": 0.0,
     "top-200": 0.49416666666666714,
     "exam": 0.5587346625766871,
     "wasted-effort": 65200
    },
    "worst_case": {
     "top-1": 0.0,
     "top-5": 0.0,
     "top-10": 0.0,
     "top-200": 0.24734999999999918,
     "exam": 0.5587346625766871,
     "wasted-effort": 65200
    }
   },
   "GP13": {
    "best_case": {
     "top-1": 0.0,
     "top-5": 0.0,
     "top-10": 0.0,
     "top-200": 0.9322,
     "exam": 0.002530674846625767,
     "wasted-effort": 270
    },
    "avg_case": {
     "top-1": 0.0,
     "top-5": 0.0,
     "top-10": 0.0,
     "top-200": 0.4896999999999995,
     "exam": 0.5587346625766871,
     "wasted-effort": 65200
    },
    "worst_case": {
     "top-1": 0.0,
     "top-5": 0.0,
     "top-10": 0.0,
     "top-200": 0.2484666666666681,
     "exam": 0.5587346625766871,
     "wasted-effort": 65200
    }
   }
  },
  "line_line": {
   "Tarantula": {
    "best_case": {
     "top-1": 0,
     "top-5": 0.0,
     "top-10": 0.0,
     "top-200": 0.9369,
     "exam": 0.0024846625766871164,
     "wasted-effort": 267
    },
    "avg_case": {
     "top-1": 0.0,
     "top-5": 0.0,
     "top-10": 0.0,
     "top-200": 0.49883333333333646,
     "exam": 0.5587346625766871,
     "wasted-effort": 65200
    },
    "worst_case": {
     "top-1": 0.0,
     "top-5": 0.0,
     "top-10": 0.0,
     "top-200": 0.24934999999999963,
     "exam": 0.5587346625766871,
     "wasted-effort": 65200
    }
   },
   "Ochiai": {
    "best_case": {
     "top-1": 0,
     "top-5": 0.0,
     "top-10": 0.0,
     "top-200": 0.9351,
     "exam": 0.0024846625766871164,
     "wasted-effort": 267
    },
    "avg_case": {
     "top-1": 0.0,
     "top-5": 0.0,
     "top-10": 0.0,
     "top-200": 0.49973333333333364,
     "exam": 0.5587346625766871,
     "wasted-effort": 65200
    },
    "worst_case": {
     "top-1": 0.0,
     "top-5": 0.0,
     "top-10": 0.0,
     "top-200": 0.2498666666666678,
     "exam": 0.5587346625766871,
     "wasted-effort": 65200
    }
   },
   "DStar": {
    "best_case": {
     "top-1": 0.0,
     "top-5": 0.0,
     "top-10": 0.0,
     "top-200": 0.9418,
     "exam": 0.00245398773006135,
     "wasted-effort": 265
    },
    "avg_case": {
     "top-1": 0.0,
     "top-5": 0.0,
     "top-10": 0.0,
     "top-200": 0.5024000000000017,
     "exam": 0.5587346625766871,
     "wasted-effort": 65200
    },
    "worst_case": {
     "top-1": 0.0,
     "top-5": 0.0,
     "top-10": 0.0,
     "top-200": 0.2523833333333343,
     "exam": 0.5587346625766871,
     "wasted-effort": 65200
    }
   },
   "Naish1": {
    "best_case": {
     "top-1": 0,
     "top-5": 0.0,
     "top-10": 0.0,
     "top-200": 0.9403,
     "exam": 0.0024846625766871164,
     "wasted-effort": 267
    },
    "avg_case": {
     "top-1": 0.0,
     "top-5": 0.0,
     "top-10": 0.0,
     "top-200": 0.502166666666668,
     "exam": 0.5587346625766871,
     "wasted-effort": 65200
    },
    "worst_case": {
     "top-1": 0.0,
     "top-5": 0.0,
     "top-10": 0.0,
     "top-200": 0.25140000000000107,
     "exam": 0.5587346625766871,
     "wasted-effort": 65200
    }
   },
   "Naish2": {
    "best_case": {
     "top-1": 0,
     "top-5": 0.0,
     "top-10": 0.0,
     "top-200": 0.9378,
     "exam": 0.0024846625766871164,
     "wasted-effort": 267
    },
    "avg_case": {
     "top-1": 0.0,
     "top-5": 0.0,
     "top-10": 0.0,
     "top-200": 0.501133333333334,
     "exam": 0.5587346625766871,
     "wasted-effort": 65200
    },
    "worst_case": {
     "top-1": 0.0,
     "top-5": 0.0,
     "top-10": 0.0,
     "top-200": 0.24824999999999983,
     "exam": 0.5587346625766871,
     "wasted-effort": 65200
    }
   },
   "GP13": {
    "best_case": {
     "top-1": 0,
     "top-5": 0.0,
     "top-10": 0.0,
     "top-200": 0.9454,
     "exam": 0.002361963190184049,
     "wasted-effort": 259
    },
    "avg_case": {
     "top-1": 0.0,
     "top-5": 0.0,
     "top-10": 0.0,
     "top-200": 0.5185666666666721,
     "exam": 0.5587346625766871,
     "wasted-effort": 65200
    },
    "worst_case": {
     "top-1": 0.0,
     "top-5": 0.0,
     "top-10": 0.0,
     "top-200": 0.25838333333333624,
     "exam": 0.5587346625766871,
     "wasted-effort": 65200
    }
   }
  },
  "line_defuse": {
   "Tarantula": {
    "best_case": {
     "top-1": 0,
     "top-5": 0.0,
     "top-10": 0.0,
     "top-200": 0.9405,
     "exam": 0.0024846625766871164,
     "wasted-effort": 267
    },
    "avg_case": {
     "top-1": 0.0,
     "top-5": 0.0,
     "top-10": 0.0,
     "top-200": 0.503866666666666,
     "exam": 0.5587346625766871,
     "wasted-effort": 65200
    },
    "worst_case": {
     "top-1": 0.0,
     "top-5": 0.0,
     "top-10": 0.0,
     "top-200": 0.24876666666666666,
     "exam": 0.5587346625766871,
     "wasted-effort": 65200
    }
   },
   "Ochiai": {
    "best_case": {
     "top-1": 0,
     "top-5": 0.0,
     "top-10": 0.0,
     "top-200": 0.9385,
     "exam": 0.0024846625766871164,
     "wasted-effort": 267
    },
    "avg_case": {
     "top-1": 0.0,
     "top-5": 0.0,
     "top-10": 0.0,
     "top-200": 0.49790000000000073,
     "exam": 0.5587346625766871,
     "wasted-effort": 65200
    },
    "worst_case": {
     "top-1": 0.0,
     "top-5": 0.0,
     "top-10": 0.0,
     "top-200": 0.2495500000000002,
     "exam": 0.5587346625766871,
     "wasted-effort": 65200
    }
   },
   "DStar": {
    "best_case": {
     "top-1": 0.0,
     "top-5": 0.0,
     "top-10": 0.0,
     "top-200": 0.9383,
     "exam": 0.00245398773006135,
     "wasted-effort": 265
    },
    "avg_case": {
     "top-1": 0.0,
     "top-5": 0.0,
     "top-10": 0.0,
     "top-200": 0.5032333333333375,
     "exam": 0.5587346625766871,
     "wasted-effort": 65200
    },
    "worst_case": {
     "top-1": 0.0,
     "top-5": 0.0,
     "top-10": 0.0,
     "top-200": 0.2513666666666674,
     "exam": 0.5587346625766871,
     "wasted-effort": 65200
    }
   },
   "Naish1": {
    "best_case": {
     "top-1": 0,
     "top-5": 0.0,
     "top-10": 0.0,
     "top-200": 0.9375,
     "exam": 0.0024846625766871164,
     "wasted-effort": 267
    },
    "avg_case": {
     "top-1": 0.0,
     "top-5": 0.0,
     "top-10": 0.0,
     "top-200": 0.49683333333333424,
     "exam": 0.5587346625766871,
     "wasted-effort": 65200
    },
    "worst_case": {
     "top-1": 0.0,
     "top-5": 0.0,
     "top-10": 0.0,
     "top-200": 0.2503000000000005,
     "exam": 0.5587346625766871,
     "wasted-effort": 65200
    }
   },
   "Naish2": {
    "best_case": {
     "top-1": 0,
     "top-5": 0.0,
     "top-10": 0.0,
     "top-200": 0.938,
     "exam": 0.0024846625766871164,
     "wasted-effort": 267
    },
    "avg_case": {
     "top-1": 0.0,
     "top-5": 0.0,
     "top-10": 0.0,
     "top-200": 0.4992666666666675,
     "exam": 0.5587346625766871,
     "wasted-effort": 65200
    },
    "worst_case": {
     "top-1": 0.0,
     "top-5": 0.0,
     "top-10": 0.0,
     "top-200": 0.2490833333333352,
     "exam": 0.5587346625766871,
     "wasted-effort": 65200
    }
   },
   "GP13": {
    "best_case": {
     "top-1": 0,
     "top-5": 0.0,
     "top-10": 0.0,
     "top-200": 0.9384,
     "exam": 0.002469325153374233,
     "wasted-effort": 266
    },
    "avg_case": {
     "top-1": 0.0,
     "top-5": 0.0,
     "top-10": 0.0,
     "top-200": 0.5045666666666704,
     "exam": 0.5587346625766871,
     "wasted-effort": 65200
    },
    "worst_case": {
     "top-1": 0.0,
     "top-5": 0.0,
     "top-10": 0.0,
     "top-200": 0.24935000000000004,
     "exam": 0.5587346625766871,
     "wasted-effort": 65200
    }
   }
  },
  "line_defuses": {
   "Tarantula": {
    "best_case": {
     "top-1": 0,
     "top-5": 0.0,
     "top-10": 0.0,
     "top-200": 0.9357,
     "exam": 0.0024846625766871164,
     "wasted-effort": 267
    },
    "avg_case": {
     "top-1": 0.0,
     "top-5": 0.0,
     "top-10": 0.0,
     "top-200": 0.500600000000003,
     "exam": 0.5587346625766871,
     "wasted-effort": 65200
    },
    "worst_case": {
     "top-1": 0.0,
     "top-5": 0.0,
     "top-10": 0.0,
     "top-200": 0.24934999999999974,
     "exam": 0.5587346625766871,
     "wasted-effort": 65200
    }
   },
   "Ochiai": {
    "best_case": {
     "top-1": 0,
     "top-5": 0.0,
     "top-10": 0.0,
     "top-200": 0.9369,
     "exam": 0.0024846625766871164,
     "wasted-effort": 267
    },
    "avg_case": {
     "top-1": 0.0,
     "top-5": 0.0,
     "top-10": 0.0,
     "top-200": 0.4972666666666667,
     "exam": 0.5587346625766871,
     "wasted-effort": 65200
    },
    "worst_case": {
     "top-1": 0.0,
     "top-5": 0.0,
     "top-10": 0.0,
     "top-200": 0.2502000000000009,
     "exam": 0.5587346625766871,
     "wasted-effort": 65200
    }
   },
   "DStar": {
    "best_case": {
     "top-1": 0.0,
     "top-5": 0.0,
     "top-10": 0.0,
     "top-200": 0.9345,
     "exam": 0.00245398773006135,
     "wasted-effort": 265
    },
    "avg_case": {
     "top-1": 0.0,
     "top-5": 0.0,
     "top-10": 0.0,
     "top-200": 0.5047666666666664,
     "exam": 0.5587346625766871,
     "wasted-effort": 65200
    },
    "worst_case": {
     "top-1": 0.0,
     "top-5": 0.0,
     "top-10": 0.0,
     "top-200": 0.25266666666666787,
     "exam": 0.5587346625766871,
     "wasted-effort": 65200
    }
   },
   "Naish1": {
    "best_case": {
     "top-1": 0,
     "top-5": 0.0,
     "top-10": 0.0,
     "top-200": 0.9397,
     "exam": 0.0024846625766871164,
     "wasted-effort": 267
    },
    "avg_case": {
     "top-1": 0.0,
     "top-5": 0.0,
     "top-10": 0.0,
     "top-200": 0.5006666666666658,
     "exam": 0.5587346625766871,
     "wasted-effort": 65200
    },
    "worst_case": {
     "top-1": 0.0,
     "top-5": 0.0,
     "top-10": 0.0,
     "top-200": 0.24818333333333284,
     "exam": 0.5587346625766871,
     "wasted-effort": 65200
    }
   },
   "Naish2": {
    "best_case": {
     "top-1": 0,
     "top-5": 0.0,
     "top-10": 0.0,
     "top-200": 0.9382,
     "exam": 0.0024846625766871164,
     "wasted-effort": 267
    },
    "avg_case": {
     "top-1": 0.0,
     "top-5": 0.0,
     "top-10": 0.0,
     "top-200": 0.5006333333333303,
     "exam": 0.5587346625766871,
     "wasted-effort": 65200
    },
    "worst_case": {
     "top-1": 0.0,
     "top-5": 0.0,
     "top-10": 0.0,
     "top-200": 0.251283333333335,
     "exam": 0.5587346625766871,
     "wasted-effort": 65200
    }
   },
   "GP13": {
    "best_case": {
     "top-1": 0,
     "top-5": 0.0,
     "top-10": 0.0,
     "top-200": 0.942,
     "exam": 0.002469325153374233,
     "wasted-effort": 266
    },
    "avg_case": {
     "top-1": 0.0,
     "top-5": 0.0,
     "top-10": 0.0,
     "top-200": 0.5008000000000022,
     "exam": 0.5587346625766871,
     "wasted-effort": 65200
    },
    "worst_case": {
     "top-1": 0.0,
     "top-5": 0.0,
     "top-10": 0.0,
     "top-200": 0.25226666666666847,
     "exam": 0.5587346625766871,
     "wasted-effort": 65200
    }
   }
  },
  "line_assert_use": {
   "Tarantula": {
    "best_case": {
     "top-1": 0,
     "top-5": 0.0,
     "top-10": 0.0,
     "top-200": 0.936,
     "exam": 0.0024846625766871164,
     "wasted-effort": 267
    },
    "avg_case": {
     "top-1": 0.0,
     "top-5": 0.0,
     "top-10": 0.0,
     "top-200": 0.5002666666666687,
     "exam": 0.5587346625766871,
     "wasted-effort": 65200
    },
    "worst_case": {
     "top-1": 0.0,
     "top-5": 0.0,
     "top-10": 0.0,
     "top-200": 0.24940000000000095,
     "exam": 0.5587346625766871,
     "wasted-effort": 65200
    }
   },
   "Ochiai": {
    "best_case": {
     "top-1": 0,
     "top-5": 0.0,
     "top-10": 0.0,
     "top-200": 0.9386,
     "exam": 0.0024846625766871164,
     "wasted-effort": 267
    },
    "avg_case": {
     "top-1": 0.0,
     "top-5": 0.0,
     "top-10": 0.0,
     "top-200": 0.49953333333333494,
     "exam": 0.5587346625766871,
     "wasted-effort": 65200
    },
    "worst_case": {
     "top-1": 0.0,
     "top-5": 0.0,
     "top-10": 0.0,
     "top-200": 0.2488166666666668,
     "exam": 0.5587346625766871,
     "wasted-effort": 65200
    }
   },
   "DStar": {
    "best_case": {
     "top-1": 0.0,
     "top-5": 0.0,
     "top-10": 0.0,
     "top-200": 0.9423,
     "exam": 0.00245398773006135,
     "wasted-effort": 265
    },
    "avg_case": {
     "top-1": 0.0,
     "top-5": 0.0,
     "top-10": 0.0,
     "top-200": 0.5011666666666663,
     "exam": 0.5587346625766871,
     "wasted-effort": 65200
    },
    "worst_case": {
     "top-1": 0.0,
     "top-5": 0.0,
     "top-10": 0.0,
     "top-200": 0.2511500000000001,
     "exam": 0.5587346625766871,
     "wasted-effort": 65200
    }
   },
   "Naish1": {
    "best_case": {
     "top-1": 0,
     "top-5": 0.0,
     "top-10": 0.0,
     "top-200": 0.9343,
     "exam": 0.0024846625766871164,
     "wasted-effort": 267
    },
    "avg_case": {
     "top-1": 0.0,
     "top-5": 0.0,
     "top-10": 0.0,
     "top-200": 0.4984000000000013,
     "exam": 0.5587346625766871,
     "wasted-effort": 65200
    },
    "worst_case": {
     "top-1": 0.0,
     "top-5": 0.0,
     "top-10": 0.0,
     "top-200": 0.24786666666666737,
     "exam": 0.5587346625766871,
     "wasted-effort": 65200
    }
   },
   "Naish2": {
    "best_case": {
     "top-1": 0,
     "top-5": 0.0,
     "top-10": 0.0,
     "top-200": 0.9395,
     "exam": 0.0024846625766871164,
     "wasted-effort": 267
    },
    "avg_case": {
     "top-1": 0.0,
     "top-5": 0.0,
     "top-10": 0.0,
     "top-200": 0.4962333333333362,
     "exam": 0.5587346625766871,
     "wasted-effort": 65200
    },
    "worst_case": {
     "top-1": 0.0,
     "top-5": 0.0,
     "top-10": 0.0,
     "top-200": 0.24846666666666575,
     "exam": 0.5587346625766871,
     "wasted-effort": 65200
    }
   },
   "GP13": {
    "best_case": {
     "top-1": 0,
     "top-5": 0.0,
     "top-10": 0.0,
     "top-200": 0.9383,
     "exam": 0.002469325153374233,
     "wasted-effort": 266
    },
    "avg_case": {
     "top-1": 0.0,
     "top-5": 0.0,
     "top-10": 0.0,
     "top-200": 0.5011666666666656,
     "exam": 0.5587346625766871,
     "wasted-effort": 65200
    },
    "worst_case": {
     "top-1": 0.0,
     "top-5": 0.0,
     "top-10": 0.0,
     "top-200": 0.2516833333333355,
     "exam": 0.5587346625766871,
     "wasted-effort": 65200
    }
   }
  },
  "line_assert_uses": {
   "Tarantula": {
    "best_case": {
     "top-1": 0,
     "top-5": 0.0,
     "top-10": 0.0,
     "top-200": 0.936,
     "exam": 0.0024846625766871164,
     "wasted-effort": 267
    },
    "avg_case": {
     "top-1": 0.0,
     "top-5": 0.0,
     "top-10": 0.0,
     "top-200": 0.498833333333332,
     "exam": 0.5587346625766871,
     "wasted-effort": 65200
    },
    "worst_case": {
     "top-1": 0.0,
     "top-5": 0.0,
     "top-10": 0.0,
     "top-200": 0.24830000000000077,
     "exam": 0.5587346625766871,
     "wasted-effort": 65200
    }
   },
   "Ochiai": {
    "best_case": {
     "top-1": 0,
     "top-5": 0.0,
     "top-10": 0.0,
     "top-200": 0.9378,
     "exam": 0.0024846625766871164,
     "wasted-effort": 267
    },
    "avg_case": {
     "top-1": 0.0,
     "top-5": 0.0,
     "top-10": 0.0,
     "top-200": 0.5018999999999993,
     "exam": 0.5587346625766871,
     "wasted-effort": 65200
    },
    "worst_case": {
     "top-1": 0.0,
     "top-5": 0.0,
     "top-10": 0.0,
     "top-200": 0.25016666666666804,
     "exam": 0.5587346625766871,
     "wasted-effort": 65200
    }
   },
   "DStar": {
    "best_case": {
     "top-1": 0.0,
     "top-5": 0.0,
     "top-10": 0.0,
     "top-200": 0.9395,
     "exam": 0.00245398773006135,
     "wasted-effort": 265
    },
    "avg_case": {
     "top-1": 0.0,
     "top-5": 0.0,
     "top-10": 0.0,
     "top-200": 0.5051333333333332,
     "exam": 0.5587346625766871,
     "wasted-effort": 65200
    },
    "worst_case": {
     "top-1": 0.0,
     "top-5": 0.0,
     "top-10": 0.0,
     "top-200": 0.2538166666666675,
     "exam": 0.5587346625766871,
     "wasted-effort": 65200
    }
   },
   "Naish1": {
    "best_case": {
     "top-1": 0,
     "top-5": 0.0,
     "top-10": 0.0,
     "top-200": 0.9409,
     "exam": 0.0024846625766871164,
     "wasted-effort": 267
    },
    "avg_case": {
     "top-1": 0.0,
     "top-5": 0.0,
     "top-10": 0.0,
     "top-200": 0.5018333333333356,
     "exam": 0.5587346625766871,
     "wasted-effort": 65200
    },
    "worst_case": {
     "top-1": 0.0,
     "top-5": 0.0,
     "top-10": 0.0,
     "top-200": 0.25151666666666816,
     "exam": 0.5587346625766871,
     "wasted-effort": 65200
    }
   },
   "Naish2": {
    "best_case": {
     "top-1": 0,
     "top-5": 0.0,
     "top-10": 0.0,
     "top-200": 0.9364,
     "exam": 0.0024846625766871164,
     "wasted-effort": 267
    },
    "avg_case": {
     "top-1": 0.0,
     "top-5": 0.0,
     "top-10": 0.0,
     "top-200": 0.49743333333332956,
     "exam": 0.5587346625766871,
     "wasted-effort": 65200
    },
    "worst_case": {
     "top-1": 0.0,
     "top-5": 0.0,
     "top-10": 0.0,
     "top-200": 0.250283333333335,
     "exam": 0.5587346625766871,
     "wasted-effort": 65200
    }
   },
   "GP13": {
    "best_case": {
     "top-1": 0,
     "top-5": 0.0,
     "top-10": 0.0,
     "top-200": 0.9418,
     "exam": 0.002469325153374233,
     "wasted-effort": 266
    },
    "avg_case": {
     "top-1": 0.0,
     "top-5": 0.0,
     "top-10": 0.0,
     "top-200": 0.5037,
     "exam": 0.5587346625766871,
     "wasted-effort": 65200
    },
    "worst_case": {
     "top-1": 0.0,
     "top-5": 0.0,
     "top-10": 0.0,
     "top-200": 0.25135000000000146,
     "exam": 0.5587346625766871,
     "wasted-effort": 65200
    }
   }
  }
 }
}