{
 "middle_1": {
  "line": {
   "Tarantula": {
    "best_case": {
     "top-1": 1,
     "top-5": 0.8251,
     "top-10": 1,
     "top-200": 1,
     "exam": 0.04,
     "wasted-effort": 1
    },
    "avg_case": {
     "top-1": 1,
     "top-5": 0.8364,
     "top-10": 1,
     "top-200": 1,
     "exam": 0.04,
     "wasted-effort": 1
    },
    "worst_case": {
     "top-1": 1.0,
     "top-5": 0.8305,
     "top-10": 1.0,
     "top-200": 1.0,
     "exam": 0.04,
     "wasted-effort": 1
    }
   },
   "Ochiai": {
    "best_case": {
     "top-1": 1,
     "top-5": 0.8367,
     "top-10": 1,
     "top-200": 1,
     "exam": 0.04,
     "wasted-effort": 1
    },
    "avg_case": {
     "top-1": 1,
     "top-5": 0.8366,
     "top-10": 1,
     "top-200": 1,
     "exam": 0.04,
     "wasted-effort": 1
    },
    "worst_case": {
     "top-1": 1.0,
     "top-5": 0.8387,
     "top-10": 1.0,
     "top-200": 1.0,
     "exam": 0.04,
     "wasted-effort": 1
    }
   },
   "DStar": {
    "best_case": {
     "top-1": 1,
     "top-5": 0.829,
     "top-10": 1,
     "top-200": 1,
     "exam": 0.04,
     "wasted-effort": 1
    },
    "avg_case": {
     "top-1": 1,
     "top-5": 0.8328,
     "top-10": 1,
     "top-200": 1,
     "exam": 0.04,
     "wasted-effort": 1
    },
    "worst_case": {
     "top-1": 1.0,
     "top-5": 0.8367,
     "top-10": 1.0,
     "top-200": 1.0,
     "exam": 0.04,
     "wasted-effort": 1
    }
   },
   "Naish1": {
    "best_case": {
     "top-1": 1,
     "top-5": 0.835,
     "top-10": 1,
     "top-200": 1,
     "exam": 0.04,
     "wasted-effort": 1
    },
    "avg_case": {
     "top-1": 1,
     "top-5": 0.8312,
     "top-10": 1,
     "top-200": 1,
     "exam": 0.04,
     "wasted-effort": 1
    },
    "worst_case": {
     "top-1": 1.0,
     "top-5": 0.83,
     "top-10": 1.0,
     "top-200": 1.0,
     "exam": 0.04,
     "wasted-effort": 1
    }
   },
   "Naish2": {
    "best_case": {
     "top-1": 1,
     "top-5": 0.8347,
     "top-10": 1,
     "top-200": 1,
     "exam": 0.04,
     "wasted-effort": 1
    },
    "avg_case": {
     "top-1": 1,
     "top-5": 0.8363,
     "top-10": 1,
     "top-200": 1,
     "exam": 0.04,
     "wasted-effort": 1
    },
    "worst_case": {
     "top-1": 1.0,
     "top-5": 0.8312,
     "top-10": 1.0,
     "top-200": 1.0,
     "exam": 0.04,
     "wasted-effort": 1
    }
   },
   "GP13": {
    "best_case": {
     "top-1": 1,
     "top-5": 0.8296,
     "top-10": 1,
     "top-200": 1,
     "exam": 0.04,
     "wasted-effort": 1
    },
    "avg_case": {
     "top-1": 1,
     "top-5": 0.8269,
     "top-10": 1,
     "top-200": 1,
     "exam": 0.04,
     "wasted-effort": 1
    },
    "worst_case": {
     "top-1": 1.0,
     "top-5": 0.8393,
     "top-10": 1.0,
     "top-200": 1.0,
     "exam": 0.04,
     "wasted-effort": 1
    }
   }
  },
  "line_line": {
   "Tarantula": {
    "best_case": {
     "top-1": 1,
     "top-5": 0.8326,
     "top-10": 1,
     "top-200": 1,
     "exam": 0.04,
     "wasted-effort": 1
    },
    "avg_case": {
     "top-1": 1,
     "top-5": 0.8332,
     "top-10": 1,
     "top-200": 1,
     "exam": 0.04,
     "wasted-effort": 1
    },
    "worst_case": {
     "top-1": 1.0,
     "top-5": 0.8383,
     "top-10": 1.0,
     "top-200": 1.0,
     "exam": 0.04,
     "wasted-effort": 1
    }
   },
   "Ochiai": {
    "best_case": {
     "top-1": 1,
     "top-5": 0.8323,
     "top-10": 1,
     "top-200": 1,
     "exam": 0.04,
     "wasted-effort": 1
    },
    "avg_case": {
     "top-1": 1,
     "top-5": 0.829,
     "top-10": 1,
     "top-200": 1,
     "exam": 0.04,
     "wasted-effort": 1
    },
    "worst_case": {
     "top-1": 1.0,
     "top-5": 0.8359,
     "top-10": 1.0,
     "top-200": 1.0,
     "exam": 0.04,
     "wasted-effort": 1
    }
   },
   "DStar": {
    "best_case": {
     "top-1": 1,
     "top-5": 0.8344,
     "top-10": 1,
     "top-200": 1,
     "exam": 0.04,
     "wasted-effort": 1
    },
    "avg_case": {
     "top-1": 1,
     "top-5": 0.8384,
     "top-10": 1,
     "top-200": 1,
     "exam": 0.04,
     "wasted-effort": 1
    },
    "worst_case": {
     "top-1": 1.0,
     "top-5": 0.8366,
     "top-10": 1.0,
     "top-200": 1.0,
     "exam": 0.04,
     "wasted-effort": 1
    }
   },
   "Naish1": {
    "best_case": {
     "top-1": 1,
     "top-5": 0.5105,
     "top-10": 1,
     "top-200": 1,
     "exam": 0.04,
     "wasted-effort": 1
    },
    "avg_case": {
     "top-1": 1,
     "top-5": 0.5032,
     "top-10": 1,
     "top-200": 1,
     "exam": 0.04,
     "wasted-effort": 1
    },
    "worst_case": {
     "top-1": 1.0,
     "top-5": 0.4982,
     "top-10": 1.0,
     "top-200": 1.0,
     "exam": 0.04,
     "wasted-effort": 1
    }
   },
   "Naish2": {
    "best_case": {
     "top-1": 1,
     "top-5": 0.8354,
     "top-10": 1,
     "top-200": 1,
     "exam": 0.04,
     "wasted-effort": 1
    },
    "avg_case": {
     "top-1": 1,
     "top-5": 0.8425,
     "top-10": 1,
     "top-200": 1,
     "exam": 0.04,
     "wasted-effort": 1
    },
    "worst_case": {
     "top-1": 1.0,
     "top-5": 0.8227,
     "top-10": 1.0,
     "top-200": 1.0,
     "exam": 0.04,
     "wasted-effort": 1
    }
   },
   "GP13": {
    "best_case": {
     "top-1": 1,
     "top-5": 0.8301,
     "top-10": 1,
     "top-200": 1,
     "exam": 0.04,
     "wasted-effort": 1
    },
    "avg_case": {
     "top-1": 1,
     "top-5": 0.8362,
     "top-10": 1,
     "top-200": 1,
     "exam": 0.04,
     "wasted-effort": 1
    },
    "worst_case": {
     "top-1": 1.0,
     "top-5": 0.8418,
     "top-10": 1.0,
     "top-200": 1.0,
     "exam": 0.04,
     "wasted-effort": 1
    }
   }
  },
  "line_defuse": {
   "Tarantula": {
    "best_case": {
     "top-1": 1,
     "top-5": 0.836,
     "top-10": 1,
     "top-200": 1,
     "exam": 0.04,
     "wasted-effort": 1
    },
    "avg_case": {
     "top-1": 1,
     "top-5": 0.8311,
     "top-10": 1,
     "top-200": 1,
     "exam": 0.04,
     "wasted-effort": 1
    },
    "worst_case": {
     "top-1": 1.0,
     "top-5": 0.8354,
     "top-10": 1.0,
     "top-200": 1.0,
     "exam": 0.04,
     "wasted-effort": 1
    }
   },
   "Ochiai": {
    "best_case": {
     "top-1": 1,
     "top-5": 0.8298,
     "top-10": 1,
     "top-200": 1,
     "exam": 0.04,
     "wasted-effort": 1
    },
    "avg_case": {
     "top-1": 1,
     "top-5": 0.8314,
     "top-10": 1,
     "top-200": 1,
     "exam": 0.04,
     "wasted-effort": 1
    },
    "worst_case": {
     "top-1": 1.0,
     "top-5": 0.8338,
     "top-10": 1.0,
     "top-200": 1.0,
     "exam": 0.04,
     "wasted-effort": 1
    }
   },
   "DStar": {
    "best_case": {
     "top-1": 1,
     "top-5": 0.8398,
     "top-10": 1,
     "top-200": 1,
     "exam": 0.04,
     "wasted-effort": 1
    },
    "avg_case": {
     "top-1": 1,
     "top-5": 0.8283,
     "top-10": 1,
     "top-200": 1,
     "exam": 0.04,
     "wasted-effort": 1
    },
    "worst_case": {
     "top-1": 1.0,
     "top-5": 0.8347,
     "top-10": 1.0,
     "top-200": 1.0,
     "exam": 0.04,
     "wasted-effort": 1
    }
   },
   "Naish1": {
    "best_case": {
     "top-1": 1,
     "top-5": 0.5002,
     "top-10": 1,
     "top-200": 1,
     "exam": 0.04,
     "wasted-effort": 1
    },
    "avg_case": {
     "top-1": 1,
     "top-5": 0.4987,
     "top-10": 1,
     "top-200": 1,
     "exam": 0.04,
     "wasted-effort": 1
    },
    "worst_case": {
     "top-1": 1.0,
     "top-5": 0.5098,
     "top-10": 1.0,
     "top-200": 1.0,
     "exam": 0.04,
     "wasted-effort": 1
    }
   },
   "Naish2": {
    "best_case": {
     "top-1": 1,
     "top-5": 0.8372,
     "top-10": 1,
     "top-200": 1,
     "exam": 0.04,
     "wasted-effort": 1
    },
    "avg_case": {
     "top-1": 1,
     "top-5": 0.8341,
     "top-10": 1,
     "top-200": 1,
     "exam": 0.04,
     "wasted-effort": 1
    },
    "worst_case": {
     "top-1": 1.0,
     "top-5": 0.8279,
     "top-10": 1.0,
     "top-200": 1.0,
     "exam": 0.04,
     "wasted-effort": 1
    }
   },
   "GP13": {
    "best_case": {
     "top-1": 1,
     "top-5": 0.838,
     "top-10": 1,
     "top-200": 1,
     "exam": 0.04,
     "wasted-effort": 1
    },
    "avg_case": {
     "top-1": 1,
     "top-5": 0.8362,
     "top-10": 1,
     "top-200": 1,
     "exam": 0.04,
     "wasted-effort": 1
    },
    "worst_case": {
     "top-1": 1.0,
     "top-5": 0.8424,
     "top-10": 1.0,
     "top-200": 1.0,
     "exam": 0.04,
     "wasted-effort": 1
    }
   }
  },
  "line_defuses": {
   "Tarantula": {
    "best_case": {
     "top-1": 1,
     "top-5": 0.8369,
     "top-10": 1,
     "top-200": 1,
     "exam": 0.04,
     "wasted-effort": 1
    },
    "avg_case": {
     "top-1": 1,
     "top-5": 0.8338,
     "top-10": 1,
     "top-200": 1,
     "exam": 0.04,
     "wasted-effort": 1
    },
    "worst_case": {
     "top-1": 1.0,
     "top-5": 0.8351,
     "top-10": 1.0,
     "top-200": 1.0,
     "exam": 0.04,
     "wasted-effort": 1
    }
   },
   "Ochiai": {
    "best_case": {
     "top-1": 1,
     "top-5": 0.8266,
     "top-10": 1,
     "top-200": 1,
     "exam": 0.04,
     "wasted-effort": 1
    },
    "avg_case": {
     "top-1": 1,
     "top-5": 0.8335,
     "top-10": 1,
     "top-200": 1,
     "exam": 0.04,
     "wasted-effort": 1
    },
    "worst_case": {
     "top-1": 1.0,
     "top-5": 0.8247,
     "top-10": 1.0,
     "top-200": 1.0,
     "exam": 0.04,
     "wasted-effort": 1
    }
   },
   "DStar": {
    "best_case": {
     "top-1": 1,
     "top-5": 0.8315,
     "top-10": 1,
     "top-200": 1,
     "exam": 0.04,
     "wasted-effort": 1
    },
    "avg_case": {
     "top-1": 1,
     "top-5": 0.8344,
     "top-10": 1,
     "top-200": 1,
     "exam": 0.04,
     "wasted-effort": 1
    },
    "worst_case": {
     "top-1": 1.0,
     "top-5": 0.8312,
     "top-10": 1.0,
     "top-200": 1.0,
     "exam": 0.04,
     "wasted-effort": 1
    }
   },
   "Naish1": {
    "best_case": {
     "top-1": 1,
     "top-5": 0.5039,
     "top-10": 1,
     "top-200": 1,
     "exam": 0.04,
     "wasted-effort": 1
    },
    "avg_case": {
     "top-1": 1,
     "top-5": 0.5,
     "top-10": 1,
     "top-200": 1,
     "exam": 0.04,
     "wasted-effort": 1
    },
    "worst_case": {
     "top-1": 1.0,
     "top-5": 0.5012,
     "top-10": 1.0,
     "top-200": 1.0,
     "exam": 0.04,
     "wasted-effort": 1
    }
   },
   "Naish2": {
    "best_case": {
     "top-1": 1,
     "top-5": 0.8357,
     "top-10": 1,
     "top-200": 1,
     "exam": 0.04,
     "wasted-effort": 1
    },
    "avg_case": {
     "top-1": 1,
     "top-5": 0.8395,
     "top-10": 1,
     "top-200": 1,
     "exam": 0.04,
     "wasted-effort": 1
    },
    "worst_case": {
     "top-1": 1.0,
     "top-5": 0.8278,
     "top-10": 1.0,
     "top-200": 1.0,
     "exam": 0.04,
     "wasted-effort": 1
    }
   },
   "GP13": {
    "best_case": {
     "top-1": 1,
     "top-5": 0.8263,
     "top-10": 1,
     "top-200": 1,
     "exam": 0.04,
     "wasted-effort": 1
    },
    "avg_case": {
     "top-1": 1,
     "top-5": 0.8324,
     "top-10": 1,
     "top-200": 1,
     "exam": 0.04,
     "wasted-effort": 1
    },
    "worst_case": {
     "top-1": 1.0,
     "top-5": 0.8306,
     "top-10": 1.0,
     "top-200": 1.0,
     "exam": 0.04,
     "wasted-effort": 1
    }
   }
  },
  "line_assert_use": {
   "Tarantula": {
    "best_case": {
     "top-1": 1,
     "top-5": 0.8299,
     "top-10": 1,
     "top-200": 1,
     "exam": 0.04,
     "wasted-effort": 1
    },
    "avg_case": {
     "top-1": 1,
     "top-5": 0.83,
     "top-10": 1,
     "top-200": 1,
     "exam": 0.04,
     "wasted-effort": 1
    },
    "worst_case": {
     "top-1": 1.0,
     "top-5": 0.8319,
     "top-10": 1.0,
     "top-200": 1.0,
     "exam": 0.04,
     "wasted-effort": 1
    }
   },
   "Ochiai": {
    "best_case": {
     "top-1": 1,
     "top-5": 0.8307,
     "top-10": 1,
     "top-200": 1,
     "exam": 0.04,
     "wasted-effort": 1
    },
    "avg_case": {
     "top-1": 1,
     "top-5": 0.8311,
     "top-10": 1,
     "top-200": 1,
     "exam": 0.04,
     "wasted-effort": 1
    },
    "worst_case": {
     "top-1": 1.0,
     "top-5": 0.8338,
     "top-10": 1.0,
     "top-200": 1.0,
     "exam": 0.04,
     "wasted-effort": 1
    }
   },
   "DStar": {
    "best_case": {
     "top-1": 1,
     "top-5": 0.832,
     "top-10": 1,
     "top-200": 1,
     "exam": 0.04,
     "wasted-effort": 1
    },
    "avg_case": {
     "top-1": 1,
     "top-5": 0.8301,
     "top-10": 1,
     "top-200": 1,
     "exam": 0.04,
     "wasted-effort": 1
    },
    "worst_case": {
     "top-1": 1.0,
     "top-5": 0.8314,
     "top-10": 1.0,
     "top-200": 1.0,
     "exam": 0.04,
     "wasted-effort": 1
    }
   },
   "Naish1": {
    "best_case": {
     "top-1": 1,
     "top-5": 0.4909,
     "top-10": 1,
     "top-200": 1,
     "exam": 0.04,
     "wasted-effort": 1
    },
    "avg_case": {
     "top-1": 1,
     "top-5": 0.5137,
     "top-10": 1,
     "top-200": 1,
     "exam": 0.04,
     "wasted-effort": 1
    },
    "worst_case": {
     "top-1": 1.0,
     "top-5": 0.4994,
     "top-10": 1.0,
     "top-200": 1.0,
     "exam": 0.04,
     "wasted-effort": 1
    }
   },
   "Naish2": {
    "best_case": {
     "top-1": 1,
     "top-5": 0.8369,
     "top-10": 1,
     "top-200": 1,
     "exam": 0.04,
     "wasted-effort": 1
    },
    "avg_case": {
     "top-1": 1,
     "top-5": 0.8361,
     "top-10": 1,
     "top-200": 1,
     "exam": 0.04,
     "wasted-effort": 1
    },
    "worst_case": {
     "top-1": 1.0,
     "top-5": 0.8319,
     "top-10": 1.0,
     "top-200": 1.0,
     "exam": 0.04,
     "wasted-effort": 1
    }
   },
   "GP13": {
    "best_case": {
     "top-1": 1,
     "top-5": 0.8305,
     "top-10": 1,
     "top-200": 1,
     "exam": 0.04,
     "wasted-effort": 1
    },
    "avg_case": {
     "top-1": 1,
     "top-5": 0.8288,
     "top-10": 1,
     "top-200": 1,
     "exam": 0.04,
     "wasted-effort": 1
    },
    "worst_case": {
     "top-1": 1.0,
     "top-5": 0.8271,
     "top-10": 1.0,
     "top-200": 1.0,
     "exam": 0.04,
     "wasted-effort": 1
    }
   }
  },
  "line_assert_uses": {
   "Tarantula": {
    "best_case": {
     "top-1": 1,
     "top-5": 0.8326,
     "top-10": 1,
     "top-200": 1,
     "exam": 0.04,
     "wasted-effort": 1
    },
    "avg_case": {
     "top-1": 1,
     "top-5": 0.8324,
     "top-10": 1,
     "top-200": 1,
     "exam": 0.04,
     "wasted-effort": 1
    },
    "worst_case": {
     "top-1": 1.0,
     "top-5": 0.8272,
     "top-10": 1.0,
     "top-200": 1.0,
     "exam": 0.04,
     "wasted-effort": 1
    }
   },
   "Ochiai": {
    "best_case": {
     "top-1": 1,
     "top-5": 0.8303,
     "top-10": 1,
     "top-200": 1,
     "exam": 0.04,
     "wasted-effort": 1
    },
    "avg_case": {
     "top-1": 1,
     "top-5": 0.8335,
     "top-10": 1,
     "top-200": 1,
     "exam": 0.04,
     "wasted-effort": 1
    },
    "worst_case": {
     "top-1": 1.0,
     "top-5": 0.8371,
     "top-10": 1.0,
     "top-200": 1.0,
     "exam": 0.04,
     "wasted-effort": 1
    }
   },
   "DStar": {
    "best_case": {
     "top-1": 1,
     "top-5": 0.8358,
     "top-10": 1,
     "top-200": 1,
     "exam": 0.04,
     "wasted-effort": 1
    },
    "avg_case": {
     "top-1": 1,
     "top-5": 0.8397,
     "top-10": 1,
     "top-200": 1,
     "exam": 0.04,
     "wasted-effort": 1
    },
    "worst_case": {
     "top-1": 1.0,
     "top-5": 0.8321,
     "top-10": 1.0,
     "top-200": 1.0,
     "exam": 0.04,
     "wasted-effort": 1
    }
   },
   "Naish1": {
    "best_case": {
     "top-1": 1,
     "top-5": 0.4964,
     "top-10": 1,
     "top-200": 1,
     "exam": 0.04,
     "wasted-effort": 1
    },
    "avg_case": {
     "top-1": 1,
     "top-5": 0.5064,
     "top-10": 1,
     "top-200": 1,
     "exam": 0.04,
     "wasted-effort": 1
    },
    "worst_case": {
     "top-1": 1.0,
     "top-5": 0.4965,
     "top-10": 1.0,
     "top-200": 1.0,
     "exam": 0.04,
     "wasted-effort": 1
    }
   },
   "Naish2": {
    "best_case": {
     "top-1": 1,
     "top-5": 0.8327,
     "top-10": 1,
     "top-200": 1,
     "exam": 0.04,
     "wasted-effort": 1
    },
    "avg_case": {
     "top-1": 1,
     "top-5": 0.8398,
     "top-10": 1,
     "top-200": 1,
     "exam": 0.04,
     "wasted-effort": 1
    },
    "worst_case": {
     "top-1": 1.0,
     "top-5": 0.8274,
     "top-10": 1.0,
     "top-200": 1.0,
     "exam": 0.04,
     "wasted-effort": 1
    }
   },
   "GP13": {
    "best_case": {
     "top-1": 1,
     "top-5": 0.8317,
     "top-10": 1,
     "top-200": 1,
     "exam": 0.04,
     "wasted-effort": 1
    },
    "avg_case": {
     "top-1": 1,
     "top-5": 0.8372,
     "top-10": 1,
     "top-200": 1,
     "exam": 0.04,
     "wasted-effort": 1
    },
    "worst_case": {
     "top-1": 1.0,
     "top-5": 0.8298,
     "top-10": 1.0,
     "top-200": 1.0,
     "exam": 0.04,
     "wasted-effort": 1
    }
   }
  }
 }
}